{
  "type": "Feature",
  "properties": {
    "gn:admin1_code":"0.0",
    "gn:asciiname":"Takongga",
    "gn:country_code":"SB",
    "gn:dem":40,
    "gn:feature_class":"P",
    "gn:feature_code":"PPL",
    "gn:name":"Takongga",
    "gn:population":0,
    "gn:timezone":"Pacific/Guadalcanal",
    "iso:country":"SB",
    "name:und_x_variant":[
        "Tambugu",
        "Tagongga",
        "Takonga",
        "Takongga"
    ],
    "wof:name":"Takongga",
    "wof:placetype":"locality"
},
  "geometry": {"coordinates":[159.61753999999999,-9.4769],"type":"Point"}
}