{
  "type": "Feature",
  "properties": {
    "gn:admin1_code":"0.0",
    "gn:asciiname":"Rerere",
    "gn:country_code":"SB",
    "gn:dem":375,
    "gn:feature_class":"P",
    "gn:feature_code":"PPL",
    "gn:name":"Rerere",
    "gn:population":0,
    "gn:timezone":"Pacific/Guadalcanal",
    "iso:country":"SB",
    "wof:name":"Rerere",
    "wof:placetype":"locality"
},
  "geometry": {"coordinates":[160.15476000000001,-9.65164],"type":"Point"}
}