{
  "type": "Feature",
  "properties": {
    "gn:admin1_code":"0.0",
    "gn:asciiname":"Iringgila",
    "gn:country_code":"SB",
    "gn:dem":3,
    "gn:feature_class":"P",
    "gn:feature_code":"PPL",
    "gn:name":"Iringgila",
    "gn:population":0,
    "gn:timezone":"Pacific/Guadalcanal",
    "iso:country":"SB",
    "wof:name":"Iringgila",
    "wof:placetype":"locality"
},
  "geometry": {"coordinates":[156.51786999999999,-7.60678],"type":"Point"}
}