{
  "type": "Feature",
  "properties": {
    "gn:admin1_code":"0.0",
    "gn:asciiname":"Suhu",
    "gn:country_code":"SB",
    "gn:dem":14,
    "gn:feature_class":"P",
    "gn:feature_code":"PPL",
    "gn:name":"Suhu",
    "gn:population":0,
    "gn:timezone":"Pacific/Guadalcanal",
    "iso:country":"SB",
    "wof:name":"Suhu",
    "wof:placetype":"locality"
},
  "geometry": {"coordinates":[160.82116000000005,-9.78645],"type":"Point"}
}