{
  "type": "Feature",
  "properties": {
    "gn:admin1_code":"0.0",
    "gn:asciiname":"Wango",
    "gn:country_code":"SB",
    "gn:dem":307,
    "gn:feature_class":"P",
    "gn:feature_code":"PPL",
    "gn:name":"Wango",
    "gn:population":0,
    "gn:timezone":"Pacific/Guadalcanal",
    "iso:country":"SB",
    "wof:name":"Wango",
    "wof:placetype":"locality"
},
  "geometry": {"coordinates":[162.05013,-10.52511],"type":"Point"}
}