{
  "type": "Feature",
  "properties": {
    "gn:admin1_code":"0.0",
    "gn:asciiname":"Lambia",
    "gn:country_code":"SB",
    "gn:dem":93,
    "gn:feature_class":"P",
    "gn:feature_code":"PPL",
    "gn:name":"Lambia",
    "gn:population":0,
    "gn:timezone":"Pacific/Guadalcanal",
    "iso:country":"SB",
    "wof:name":"Lambia",
    "wof:placetype":"locality"
},
  "geometry": {"coordinates":[160.08333000000005,-9.81667],"type":"Point"}
}