{
  "type": "Feature",
  "properties": {
    "gn:admin1_code":"0.0",
    "gn:asciiname":"Taramata",
    "gn:country_code":"SB",
    "gn:dem":31,
    "gn:feature_class":"P",
    "gn:feature_code":"PPL",
    "gn:name":"Taramata",
    "gn:population":0,
    "gn:timezone":"Pacific/Guadalcanal",
    "iso:country":"SB",
    "wof:name":"Taramata",
    "wof:placetype":"locality"
},
  "geometry": {"coordinates":[161.42545000000001,-9.48356],"type":"Point"}
}