{
  "type": "Feature",
  "properties": {
    "gn:admin1_code":"0.0",
    "gn:asciiname":"Aupono",
    "gn:country_code":"SB",
    "gn:dem":99,
    "gn:feature_class":"P",
    "gn:feature_code":"PPL",
    "gn:name":"Aupono",
    "gn:population":0,
    "gn:timezone":"Pacific/Guadalcanal",
    "iso:country":"SB",
    "wof:name":"Aupono",
    "wof:placetype":"locality"
},
  "geometry": {"coordinates":[161.16978,-9.04249],"type":"Point"}
}