{
  "type": "Feature",
  "properties": {
    "gn:admin1_code":"0.0",
    "gn:asciiname":"Mbara Parilonga",
    "gn:country_code":"SB",
    "gn:dem":9,
    "gn:feature_class":"P",
    "gn:feature_code":"PPL",
    "gn:name":"Mbara Parilonga",
    "gn:population":0,
    "gn:timezone":"Pacific/Guadalcanal",
    "iso:country":"SB",
    "name:und_x_variant":[
        "Oula",
        "Mbara Parilonga"
    ],
    "wof:name":"Mbara Parilonga",
    "wof:placetype":"locality"
},
  "geometry": {"coordinates":[160.50936999999999,-9.53779],"type":"Point"}
}