{
  "type": "Feature",
  "properties": {
    "gn:admin1_code":"0.0",
    "gn:asciiname":"Fifihu",
    "gn:country_code":"SB",
    "gn:dem":252,
    "gn:feature_class":"P",
    "gn:feature_code":"PPL",
    "gn:name":"Fifihu",
    "gn:population":0,
    "gn:timezone":"Pacific/Guadalcanal",
    "iso:country":"SB",
    "wof:name":"Fifihu",
    "wof:placetype":"locality"
},
  "geometry": {"coordinates":[159.59993,-8.30174],"type":"Point"}
}