{
  "type": "Feature",
  "properties": {
    "gn:admin1_code":"0.0",
    "gn:asciiname":"Visovaso",
    "gn:country_code":"SB",
    "gn:dem":23,
    "gn:feature_class":"P",
    "gn:feature_code":"PPL",
    "gn:name":"Visovaso",
    "gn:population":0,
    "gn:timezone":"Pacific/Guadalcanal",
    "iso:country":"SB",
    "wof:name":"Visovaso",
    "wof:placetype":"locality"
},
  "geometry": {"coordinates":[156.78031999999999,-6.77165],"type":"Point"}
}