{
  "type": "Feature",
  "properties": {
    "gn:admin1_code":"0.0",
    "gn:asciiname":"Sulukiai",
    "gn:country_code":"SB",
    "gn:dem":26,
    "gn:feature_class":"P",
    "gn:feature_code":"PPL",
    "gn:name":"Sulukiai",
    "gn:population":0,
    "gn:timezone":"Pacific/Guadalcanal",
    "iso:country":"SB",
    "name:und_x_variant":[
        "Siruria",
        "Sirukia",
        "Sulukiai"
    ],
    "wof:name":"Sulukiai",
    "wof:placetype":"locality"
},
  "geometry": {"coordinates":[155.75044,-7.09918],"type":"Point"}
}