{
  "type": "Feature",
  "properties": {
    "gn:admin1_code":"0.0",
    "gn:asciiname":"Narowai",
    "gn:country_code":"SB",
    "gn:dem":6,
    "gn:feature_class":"P",
    "gn:feature_code":"PPL",
    "gn:name":"Narowai",
    "gn:population":0,
    "gn:timezone":"Pacific/Guadalcanal",
    "iso:country":"SB",
    "wof:name":"Narowai",
    "wof:placetype":"locality"
},
  "geometry": {"coordinates":[156.76719,-7.79185],"type":"Point"}
}