{
  "type": "Feature",
  "properties": {
    "gn:admin1_code":"0.0",
    "gn:asciiname":"Na Kuma",
    "gn:country_code":"SB",
    "gn:dem":408,
    "gn:feature_class":"P",
    "gn:feature_code":"PPL",
    "gn:name":"Na Kuma",
    "gn:population":0,
    "gn:timezone":"Pacific/Guadalcanal",
    "iso:country":"SB",
    "wof:name":"Na Kuma",
    "wof:placetype":"locality"
},
  "geometry": {"coordinates":[160.65593999999999,-9.80967],"type":"Point"}
}