{
  "type": "Feature",
  "properties": {
    "gn:admin1_code":"0.0",
    "gn:asciiname":"Pululaha",
    "gn:country_code":"SB",
    "gn:dem":14,
    "gn:feature_class":"P",
    "gn:feature_code":"PPL",
    "gn:name":"Pululaha",
    "gn:population":0,
    "gn:timezone":"Pacific/Guadalcanal",
    "iso:country":"SB",
    "wof:name":"Pululaha",
    "wof:placetype":"locality"
},
  "geometry": {"coordinates":[161.40807000000001,-9.61556],"type":"Point"}
}