{
  "type": "Feature",
  "properties": {
    "gn:admin1_code":"0.0",
    "gn:asciiname":"Matango",
    "gn:country_code":"SB",
    "gn:dem":14,
    "gn:feature_class":"P",
    "gn:feature_code":"PPL",
    "gn:name":"Matango",
    "gn:population":0,
    "gn:timezone":"Pacific/Guadalcanal",
    "iso:country":"SB",
    "name:fra_x_preferred":[
        "Matango"
    ],
    "name:jpn_x_preferred":[
        "\u30de\u30bf\u30f3\u30b4"
    ],
    "name:ron_x_preferred":[
        "Matango"
    ],
    "name:zho_x_preferred":[
        "\u746a\u5766\u6208"
    ],
    "wof:name":"Matango",
    "wof:placetype":"locality"
},
  "geometry": {"coordinates":[160.72492,-9.71561],"type":"Point"}
}