{
  "type": "Feature",
  "properties": {
    "gn:admin1_code":"0.0",
    "gn:asciiname":"Raolo",
    "gn:country_code":"SB",
    "gn:dem":3,
    "gn:feature_class":"P",
    "gn:feature_code":"PPL",
    "gn:name":"Raolo",
    "gn:population":0,
    "gn:timezone":"Pacific/Guadalcanal",
    "iso:country":"SB",
    "wof:name":"Raolo",
    "wof:placetype":"locality"
},
  "geometry": {"coordinates":[160.7226,-8.8147],"type":"Point"}
}