{
  "type": "Feature",
  "properties": {
    "gn:admin1_code":"0.0",
    "gn:asciiname":"Kwaiorua",
    "gn:country_code":"SB",
    "gn:dem":12,
    "gn:feature_class":"P",
    "gn:feature_code":"PPL",
    "gn:name":"Kwaiorua",
    "gn:population":0,
    "gn:timezone":"Pacific/Guadalcanal",
    "iso:country":"SB",
    "name:und_x_variant":[
        "Maanakafo",
        "Kwaiorua"
    ],
    "wof:name":"Kwaiorua",
    "wof:placetype":"locality"
},
  "geometry": {"coordinates":[160.58323999999999,-8.39424],"type":"Point"}
}