{
  "type": "Feature",
  "properties": {
    "gn:admin1_code":"0.0",
    "gn:asciiname":"Tuo",
    "gn:country_code":"SB",
    "gn:dem":1,
    "gn:feature_class":"P",
    "gn:feature_code":"PPL",
    "gn:name":"Tuo",
    "gn:population":0,
    "gn:timezone":"Pacific/Guadalcanal",
    "iso:country":"SB",
    "name:jpn_x_preferred":[
        "\u30bf"
    ],
    "wof:name":"Tuo",
    "wof:placetype":"locality"
},
  "geometry": {"coordinates":[166.23333,-10.26667],"type":"Point"}
}