{
  "type": "Feature",
  "properties": {
    "gn:admin1_code":"0.0",
    "gn:asciiname":"Tuo",
    "gn:country_code":"SB",
    "gn:dem":1,
    "gn:feature_class":"P",
    "gn:feature_code":"PPL",
    "gn:name":"Tuo",
    "gn:population":0,
    "gn:timezone":"Pacific/Guadalcanal",
    "iso:country":"SB",
    "name:ara_x_preferred":[
        "\u062a\u0648"
    ],
    "name:ben_x_preferred":[
        "\u09a4\u09c1\u0993"
    ],
    "name:ell_x_preferred":[
        "\u03a4\u03bf\u03c5\u03cc"
    ],
    "name:fas_x_preferred":[
        "\u062a\u0648"
    ],
    "name:heb_x_preferred":[
        "\u05d8\u05d5\u05d0\u05d5"
    ],
    "name:hin_x_preferred":[
        "\u091f\u0942\u0913"
    ],
    "name:hun_x_preferred":[
        "Tuo"
    ],
    "name:ind_x_preferred":[
        "Tuo"
    ],
    "name:jpn_x_preferred":[
        "\u30bf"
    ],
    "name:pol_x_preferred":[
        "Tuo"
    ],
    "name:por_x_preferred":[
        "Tuo"
    ],
    "name:tur_x_preferred":[
        "Tuo"
    ],
    "name:ukr_x_preferred":[
        "\u0422\u0443\u043e"
    ],
    "name:urd_x_preferred":[
        "\u0679\u06cc\u0648"
    ],
    "name:vie_x_preferred":[
        "S\u00f4ng Tuo"
    ],
    "wof:name":"Tuo",
    "wof:placetype":"locality"
},
  "geometry": {"coordinates":[166.23333,-10.26667],"type":"Point"}
}