{
  "type": "Feature",
  "properties": {
    "gn:admin1_code":"0.0",
    "gn:asciiname":"Chocho",
    "gn:country_code":"SB",
    "gn:dem":19,
    "gn:feature_class":"P",
    "gn:feature_code":"PPL",
    "gn:name":"Chocho",
    "gn:population":0,
    "gn:timezone":"Pacific/Guadalcanal",
    "iso:country":"SB",
    "name:deu_x_preferred":[
        "Chocho"
    ],
    "name:spa_x_preferred":[
        "Chocho"
    ],
    "wof:name":"Chocho",
    "wof:placetype":"locality"
},
  "geometry": {"coordinates":[160.13578000000001,-9.81546],"type":"Point"}
}