{
  "type": "Feature",
  "properties": {
    "gn:admin1_code":"0.0",
    "gn:asciiname":"Nata",
    "gn:country_code":"SB",
    "gn:dem":311,
    "gn:feature_class":"P",
    "gn:feature_code":"PPL",
    "gn:name":"Nata",
    "gn:population":0,
    "gn:timezone":"Pacific/Guadalcanal",
    "iso:country":"SB",
    "name:ceb_x_preferred":[
        "Nata"
    ],
    "name:deu_x_preferred":[
        "Nata"
    ],
    "name:ell_x_preferred":[
        "\u039d\u03ac\u03c4\u03b1"
    ],
    "name:fra_x_preferred":[
        "Nata"
    ],
    "name:glg_x_preferred":[
        "Nata"
    ],
    "name:ita_x_preferred":[
        "Nata"
    ],
    "name:por_x_preferred":[
        "Nata"
    ],
    "name:spa_x_preferred":[
        "Nata"
    ],
    "name:swe_x_preferred":[
        "Nata"
    ],
    "wof:name":"Nata",
    "wof:placetype":"locality"
},
  "geometry": {"coordinates":[160.18333000000001,-9.78333],"type":"Point"}
}