{
  "type": "Feature",
  "properties": {
    "gn:admin1_code":"0.0",
    "gn:asciiname":"Songgulu",
    "gn:country_code":"SB",
    "gn:dem":20,
    "gn:feature_class":"P",
    "gn:feature_code":"PPL",
    "gn:name":"Songgulu",
    "gn:population":0,
    "gn:timezone":"Pacific/Guadalcanal",
    "iso:country":"SB",
    "wof:name":"Songgulu",
    "wof:placetype":"locality"
},
  "geometry": {"coordinates":[160.17931999999999,-9.8156],"type":"Point"}
}