{
  "type": "Feature",
  "properties": {
    "gn:admin1_code":"0.0",
    "gn:asciiname":"Kekena",
    "gn:country_code":"SB",
    "gn:dem":26,
    "gn:feature_class":"P",
    "gn:feature_code":"PPL",
    "gn:name":"Kekena",
    "gn:population":0,
    "gn:timezone":"Pacific/Guadalcanal",
    "iso:country":"SB",
    "wof:name":"Kekena",
    "wof:placetype":"locality"
},
  "geometry": {"coordinates":[160.29908,-9.48568],"type":"Point"}
}