{
  "type": "Feature",
  "properties": {
    "gn:admin1_code":"0.0",
    "gn:asciiname":"Mbambanakira",
    "gn:country_code":"SB",
    "gn:dem":21,
    "gn:feature_class":"P",
    "gn:feature_code":"PPL",
    "gn:name":"Mbambanakira",
    "gn:population":0,
    "gn:timezone":"Pacific/Guadalcanal",
    "iso:country":"SB",
    "wof:name":"Mbambanakira",
    "wof:placetype":"locality"
},
  "geometry": {"coordinates":[159.82956999999999,-9.75025],"type":"Point"}
}