{
  "type": "Feature",
  "properties": {
    "gn:admin1_code":"0.0",
    "gn:asciiname":"Kerepei",
    "gn:country_code":"SB",
    "gn:dem":53,
    "gn:feature_class":"P",
    "gn:feature_code":"PPL",
    "gn:name":"Kerepei",
    "gn:population":0,
    "gn:timezone":"Pacific/Guadalcanal",
    "iso:country":"SB",
    "name:und_x_variant":[
        "Kerepai",
        "Kerepei"
    ],
    "wof:name":"Kerepei",
    "wof:placetype":"locality"
},
  "geometry": {"coordinates":[161.73283000000001,-10.28211],"type":"Point"}
}