{
  "type": "Feature",
  "properties": {
    "gn:admin1_code":"0.0",
    "gn:asciiname":"Riusoru",
    "gn:country_code":"SB",
    "gn:dem":118,
    "gn:feature_class":"P",
    "gn:feature_code":"PPL",
    "gn:name":"Riusoru",
    "gn:population":0,
    "gn:timezone":"Pacific/Guadalcanal",
    "iso:country":"SB",
    "wof:name":"Riusoru",
    "wof:placetype":"locality"
},
  "geometry": {"coordinates":[159.68433999999999,-8.25992],"type":"Point"}
}