{
  "type": "Feature",
  "properties": {
    "gn:admin1_code":"0.0",
    "gn:asciiname":"Ngaliturara",
    "gn:country_code":"SB",
    "gn:dem":202,
    "gn:feature_class":"P",
    "gn:feature_code":"PPL",
    "gn:name":"Ngaliturara",
    "gn:population":0,
    "gn:timezone":"Pacific/Guadalcanal",
    "iso:country":"SB",
    "wof:name":"Ngaliturara",
    "wof:placetype":"locality"
},
  "geometry": {"coordinates":[160.06361000000001,-9.79608],"type":"Point"}
}