{
  "type": "Feature",
  "properties": {
    "gn:admin1_code":"0.0",
    "gn:asciiname":"Andi",
    "gn:country_code":"SB",
    "gn:dem":443,
    "gn:feature_class":"P",
    "gn:feature_code":"PPL",
    "gn:name":"Andi",
    "gn:population":0,
    "gn:timezone":"Pacific/Guadalcanal",
    "iso:country":"SB",
    "name:cat_x_preferred":[
        "Andi"
    ],
    "name:ceb_x_preferred":[
        "Andi"
    ],
    "name:fra_x_preferred":[
        "Andi"
    ],
    "name:nld_x_preferred":[
        "Andi"
    ],
    "name:rus_x_preferred":[
        "\u0410\u043d\u0434\u0438"
    ],
    "name:slv_x_preferred":[
        "Andi"
    ],
    "wof:name":"Andi",
    "wof:placetype":"locality"
},
  "geometry": {"coordinates":[160.61667,-8.36667],"type":"Point"}
}