{
  "type": "Feature",
  "properties": {
    "gn:admin1_code":"0.0",
    "gn:asciiname":"Savilu",
    "gn:country_code":"SB",
    "gn:dem":65,
    "gn:feature_class":"P",
    "gn:feature_code":"PPL",
    "gn:name":"Savilu",
    "gn:population":0,
    "gn:timezone":"Pacific/Guadalcanal",
    "iso:country":"SB",
    "wof:name":"Savilu",
    "wof:placetype":"locality"
},
  "geometry": {"coordinates":[160.55008000000001,-9.61969],"type":"Point"}
}