{
  "type": "Feature",
  "properties": {
    "gn:admin1_code":"0.0",
    "gn:asciiname":"Paru",
    "gn:country_code":"SB",
    "gn:dem":13,
    "gn:feature_class":"P",
    "gn:feature_code":"PPL",
    "gn:name":"Paru",
    "gn:population":0,
    "gn:timezone":"Pacific/Guadalcanal",
    "iso:country":"SB",
    "name:ast_x_preferred":[
        "Paru"
    ],
    "name:fra_x_preferred":[
        "Paru"
    ],
    "name:scn_x_preferred":[
        "Paru"
    ],
    "wof:name":"Paru",
    "wof:placetype":"locality"
},
  "geometry": {"coordinates":[159.65551000000005,-9.27188],"type":"Point"}
}