{
  "type": "Feature",
  "properties": {
    "gn:admin1_code":"0.0",
    "gn:asciiname":"Kuva Kei",
    "gn:country_code":"SB",
    "gn:dem":540,
    "gn:feature_class":"P",
    "gn:feature_code":"PPL",
    "gn:name":"Kuva Kei",
    "gn:population":0,
    "gn:timezone":"Pacific/Guadalcanal",
    "iso:country":"SB",
    "wof:name":"Kuva Kei",
    "wof:placetype":"locality"
},
  "geometry": {"coordinates":[160.38645,-9.75186],"type":"Point"}
}