{
  "type": "Feature",
  "properties": {
    "gn:admin1_code":"0.0",
    "gn:asciiname":"Rio'ao",
    "gn:country_code":"SB",
    "gn:dem":14,
    "gn:feature_class":"P",
    "gn:feature_code":"PPL",
    "gn:name":"Rio\u2019ao",
    "gn:population":0,
    "gn:timezone":"Pacific/Guadalcanal",
    "iso:country":"SB",
    "wof:name":"Rio'ao",
    "wof:placetype":"locality"
},
  "geometry": {"coordinates":[161.23922999999999,-9.18493],"type":"Point"}
}