{
  "type": "Feature",
  "properties": {
    "gn:admin1_code":"0.0",
    "gn:asciiname":"Huru",
    "gn:country_code":"SB",
    "gn:dem":248,
    "gn:feature_class":"P",
    "gn:feature_code":"PPL",
    "gn:name":"Huru",
    "gn:population":0,
    "gn:timezone":"Pacific/Guadalcanal",
    "iso:country":"SB",
    "wof:name":"Huru",
    "wof:placetype":"locality"
},
  "geometry": {"coordinates":[161.16666999999995,-9.21667],"type":"Point"}
}