{
  "type": "Feature",
  "properties": {
    "gn:admin1_code":"0.0",
    "gn:asciiname":"Fulifo'oe",
    "gn:country_code":"SB",
    "gn:dem":41,
    "gn:feature_class":"P",
    "gn:feature_code":"PPL",
    "gn:name":"Fulifo\u2019oe",
    "gn:population":0,
    "gn:timezone":"Pacific/Guadalcanal",
    "iso:country":"SB",
    "wof:name":"Fulifo'oe",
    "wof:placetype":"locality"
},
  "geometry": {"coordinates":[160.57900000000001,-8.33194],"type":"Point"}
}