{
  "type": "Feature",
  "properties": {
    "gn:admin1_code":"0.0",
    "gn:asciiname":"Haroro",
    "gn:country_code":"SB",
    "gn:dem":5,
    "gn:feature_class":"P",
    "gn:feature_code":"PPL",
    "gn:name":"Haroro",
    "gn:population":0,
    "gn:timezone":"Pacific/Guadalcanal",
    "iso:country":"SB",
    "name:und_x_variant":[
        "Naroro",
        "Haroro"
    ],
    "wof:name":"Haroro",
    "wof:placetype":"locality"
},
  "geometry": {"coordinates":[160.11525,-9.02525],"type":"Point"}
}