{
  "type": "Feature",
  "properties": {
    "gn:admin1_code":"0.0",
    "gn:asciiname":"Oesambe",
    "gn:country_code":"SB",
    "gn:dem":11,
    "gn:feature_class":"P",
    "gn:feature_code":"PPL",
    "gn:name":"Oesambe",
    "gn:population":0,
    "gn:timezone":"Pacific/Guadalcanal",
    "iso:country":"SB",
    "name:und_x_variant":[
        "Oisabe",
        "Oesambe"
    ],
    "wof:name":"Oesambe",
    "wof:placetype":"locality"
},
  "geometry": {"coordinates":[157.33843999999999,-7.40604],"type":"Point"}
}