{
  "type": "Feature",
  "properties": {
    "gn:admin1_code":"0.0",
    "gn:asciiname":"Malo",
    "gn:country_code":"SB",
    "gn:dem":9,
    "gn:feature_class":"P",
    "gn:feature_code":"PPL",
    "gn:name":"Malo",
    "gn:population":0,
    "gn:timezone":"Pacific/Guadalcanal",
    "iso:country":"SB",
    "name:bul_x_preferred":[
        "\u041c\u0430\u043b\u043e"
    ],
    "name:ceb_x_preferred":[
        "Malo"
    ],
    "name:deu_x_preferred":[
        "Malo"
    ],
    "name:epo_x_preferred":[
        "Malo"
    ],
    "name:eus_x_preferred":[
        "Malo"
    ],
    "name:fin_x_preferred":[
        "Malo"
    ],
    "name:fra_x_preferred":[
        "Malo"
    ],
    "name:glg_x_preferred":[
        "Malo"
    ],
    "name:ind_x_preferred":[
        "Malo"
    ],
    "name:ita_x_preferred":[
        "Malo"
    ],
    "name:nld_x_preferred":[
        "Malo"
    ],
    "name:ron_x_preferred":[
        "Malo"
    ],
    "name:rus_x_preferred":[
        "\u041c\u0430\u043b\u043e"
    ],
    "name:spa_x_preferred":[
        "Malo"
    ],
    "name:swe_x_preferred":[
        "Malo"
    ],
    "wof:name":"Malo",
    "wof:placetype":"locality"
},
  "geometry": {"coordinates":[165.79893999999999,-10.69859],"type":"Point"}
}