{
  "type": "Feature",
  "properties": {
    "gn:admin1_code":"0.0",
    "gn:asciiname":"Tamami",
    "gn:country_code":"SB",
    "gn:dem":20,
    "gn:feature_class":"P",
    "gn:feature_code":"PPL",
    "gn:name":"Tamami",
    "gn:population":0,
    "gn:timezone":"Pacific/Guadalcanal",
    "iso:country":"SB",
    "wof:name":"Tamami",
    "wof:placetype":"locality"
},
  "geometry": {"coordinates":[159.60401999999999,-9.53407],"type":"Point"}
}