{
  "type": "Feature",
  "properties": {
    "gn:admin1_code":"0.0",
    "gn:asciiname":"Komuvaolu",
    "gn:country_code":"SB",
    "gn:dem":13,
    "gn:feature_class":"P",
    "gn:feature_code":"PPL",
    "gn:name":"Komuvaolu",
    "gn:population":0,
    "gn:timezone":"Pacific/Guadalcanal",
    "iso:country":"SB",
    "name:und_x_variant":[
        "Komovaolo",
        "Komuvaolu"
    ],
    "wof:name":"Komuvaolu",
    "wof:placetype":"locality"
},
  "geometry": {"coordinates":[160.57631999999995,-9.91736],"type":"Point"}
}