{
  "type": "Feature",
  "properties": {
    "gn:admin1_code":"0.0",
    "gn:asciiname":"Ulusughu",
    "gn:country_code":"SB",
    "gn:dem":13,
    "gn:feature_class":"P",
    "gn:feature_code":"PPL",
    "gn:name":"Ulusughu",
    "gn:population":0,
    "gn:timezone":"Pacific/Guadalcanal",
    "iso:country":"SB",
    "name:und_x_variant":[
        "Ulusugo",
        "Ulusugu",
        "Ulusughu"
    ],
    "wof:name":"Ulusughu",
    "wof:placetype":"locality"
},
  "geometry": {"coordinates":[160.20925,-9.81201],"type":"Point"}
}