{
  "type": "Feature",
  "properties": {
    "gn:admin1_code":"0.0",
    "gn:asciiname":"Leovatu",
    "gn:country_code":"SB",
    "gn:dem":78,
    "gn:feature_class":"P",
    "gn:feature_code":"PPL",
    "gn:name":"Leovatu",
    "gn:population":0,
    "gn:timezone":"Pacific/Guadalcanal",
    "iso:country":"SB",
    "wof:name":"Leovatu",
    "wof:placetype":"locality"
},
  "geometry": {"coordinates":[160.56691000000001,-9.67391],"type":"Point"}
}