{
  "type": "Feature",
  "properties": {
    "gn:admin1_code":"0.0",
    "gn:asciiname":"Aligegeo",
    "gn:country_code":"SB",
    "gn:dem":24,
    "gn:feature_class":"P",
    "gn:feature_code":"PPL",
    "gn:name":"Aligegeo",
    "gn:population":0,
    "gn:timezone":"Pacific/Guadalcanal",
    "iso:country":"SB",
    "wof:name":"Aligegeo",
    "wof:placetype":"locality"
},
  "geometry": {"coordinates":[160.69186999999999,-8.74946],"type":"Point"}
}