{
  "type": "Feature",
  "properties": {
    "gn:admin1_code":"0.0",
    "gn:asciiname":"Kolokiki",
    "gn:country_code":"SB",
    "gn:dem":27,
    "gn:feature_class":"P",
    "gn:feature_code":"PPL",
    "gn:name":"Kolokiki",
    "gn:population":0,
    "gn:timezone":"Pacific/Guadalcanal",
    "iso:country":"SB",
    "wof:name":"Kolokiki",
    "wof:placetype":"locality"
},
  "geometry": {"coordinates":[160.59298999999999,-9.92084],"type":"Point"}
}