{
  "type": "Feature",
  "properties": {
    "gn:admin1_code":"0.0",
    "gn:asciiname":"Mbilikovu",
    "gn:country_code":"SB",
    "gn:dem":5,
    "gn:feature_class":"P",
    "gn:feature_code":"PPL",
    "gn:name":"Mbilikovu",
    "gn:population":0,
    "gn:timezone":"Pacific/Guadalcanal",
    "iso:country":"SB",
    "name:und_x_variant":[
        "Bilikovu",
        "Mbilikovu"
    ],
    "wof:name":"Mbilikovu",
    "wof:placetype":"locality"
},
  "geometry": {"coordinates":[159.71021999999999,-9.68134],"type":"Point"}
}