{
  "type": "Feature",
  "properties": {
    "gn:admin1_code":"0.0",
    "gn:asciiname":"Chombonavaka",
    "gn:country_code":"SB",
    "gn:dem":6,
    "gn:feature_class":"P",
    "gn:feature_code":"PPL",
    "gn:name":"Chombonavaka",
    "gn:population":0,
    "gn:timezone":"Pacific/Guadalcanal",
    "iso:country":"SB",
    "wof:name":"Chombonavaka",
    "wof:placetype":"locality"
},
  "geometry": {"coordinates":[159.65000000000001,-9.58333],"type":"Point"}
}