{
  "type": "Feature",
  "properties": {
    "gn:admin1_code":"0.0",
    "gn:asciiname":"Ngambe (Ambi)",
    "gn:country_code":"SB",
    "gn:dem":139,
    "gn:feature_class":"P",
    "gn:feature_code":"PPL",
    "gn:name":"Ngambe (Ambi)",
    "gn:population":0,
    "gn:timezone":"Pacific/Guadalcanal",
    "iso:country":"SB",
    "wof:name":"Ngambe (Ambi)",
    "wof:placetype":"locality"
},
  "geometry": {"coordinates":[166.81666999999999,-11.68333],"type":"Point"}
}