{
  "type": "Feature",
  "properties": {
    "gn:admin1_code":"0.0",
    "gn:asciiname":"Nusu",
    "gn:country_code":"SB",
    "gn:dem":559,
    "gn:feature_class":"P",
    "gn:feature_code":"PPL",
    "gn:name":"Nusu",
    "gn:population":0,
    "gn:timezone":"Pacific/Guadalcanal",
    "iso:country":"SB",
    "wof:name":"Nusu",
    "wof:placetype":"locality"
},
  "geometry": {"coordinates":[159.59421,-8.18304],"type":"Point"}
}