{
  "type": "Feature",
  "properties": {
    "gn:admin1_code":"0.0",
    "gn:asciiname":"Komuporo",
    "gn:country_code":"SB",
    "gn:dem":17,
    "gn:feature_class":"P",
    "gn:feature_code":"PPL",
    "gn:name":"Komuporo",
    "gn:population":0,
    "gn:timezone":"Pacific/Guadalcanal",
    "iso:country":"SB",
    "wof:name":"Komuporo",
    "wof:placetype":"locality"
},
  "geometry": {"coordinates":[160.16130000000001,-9.4106],"type":"Point"}
}