{
  "type": "Feature",
  "properties": {
    "gn:admin1_code":"0.0",
    "gn:asciiname":"Mbanimbani",
    "gn:country_code":"SB",
    "gn:dem":64,
    "gn:feature_class":"P",
    "gn:feature_code":"PPL",
    "gn:name":"Mbanimbani",
    "gn:population":0,
    "gn:timezone":"Pacific/Guadalcanal",
    "iso:country":"SB",
    "name:und_x_variant":[
        "Banimbari",
        "Mbanimbani"
    ],
    "wof:name":"Mbanimbani",
    "wof:placetype":"locality"
},
  "geometry": {"coordinates":[156.58926,-6.66015],"type":"Point"}
}