{
  "type": "Feature",
  "properties": {
    "gn:admin1_code":"0.0",
    "gn:asciiname":"Chea",
    "gn:country_code":"SB",
    "gn:dem":8,
    "gn:feature_class":"P",
    "gn:feature_code":"PPL",
    "gn:name":"Chea",
    "gn:population":0,
    "gn:timezone":"Pacific/Guadalcanal",
    "iso:country":"SB",
    "wof:name":"Chea",
    "wof:placetype":"locality"
},
  "geometry": {"coordinates":[158.01586,-8.5022],"type":"Point"}
}