{
  "type": "Feature",
  "properties": {
    "gn:admin1_code":"0.0",
    "gn:asciiname":"Kurilaka",
    "gn:country_code":"SB",
    "gn:dem":33,
    "gn:feature_class":"P",
    "gn:feature_code":"PPL",
    "gn:name":"Kurilaka",
    "gn:population":0,
    "gn:timezone":"Pacific/Guadalcanal",
    "iso:country":"SB",
    "wof:name":"Kurilaka",
    "wof:placetype":"locality"
},
  "geometry": {"coordinates":[160.65566999999999,-9.90829],"type":"Point"}
}