{
  "type": "Feature",
  "properties": {
    "gn:admin1_code":"0.0",
    "gn:asciiname":"Na Kambi",
    "gn:country_code":"SB",
    "gn:dem":788,
    "gn:feature_class":"P",
    "gn:feature_code":"PPL",
    "gn:name":"Na Kambi",
    "gn:population":0,
    "gn:timezone":"Pacific/Guadalcanal",
    "iso:country":"SB",
    "wof:name":"Na Kambi",
    "wof:placetype":"locality"
},
  "geometry": {"coordinates":[160.37353999999999,-9.70001],"type":"Point"}
}