{
  "type": "Feature",
  "properties": {
    "gn:admin1_code":"0.0",
    "gn:asciiname":"Koghe",
    "gn:country_code":"SB",
    "gn:dem":263,
    "gn:feature_class":"P",
    "gn:feature_code":"PPL",
    "gn:name":"Koghe",
    "gn:population":0,
    "gn:timezone":"Pacific/Guadalcanal",
    "iso:country":"SB",
    "wof:name":"Koghe",
    "wof:placetype":"locality"
},
  "geometry": {"coordinates":[159.5934,-8.27404],"type":"Point"}
}