{
  "type": "Feature",
  "properties": {
    "gn:admin1_code":"0.0",
    "gn:asciiname":"Tuvu",
    "gn:country_code":"SB",
    "gn:dem":8,
    "gn:feature_class":"P",
    "gn:feature_code":"PPL",
    "gn:name":"Tuvu",
    "gn:population":0,
    "gn:timezone":"Pacific/Guadalcanal",
    "iso:country":"SB",
    "name:und_x_variant":[
        "Rabu",
        "Tuvu"
    ],
    "wof:name":"Tuvu",
    "wof:placetype":"locality"
},
  "geometry": {"coordinates":[160.47524999999999,-9.51026],"type":"Point"}
}