{
  "type": "Feature",
  "properties": {
    "gn:admin1_code":"0.0",
    "gn:asciiname":"Sesedo",
    "gn:country_code":"SB",
    "gn:dem":10,
    "gn:feature_class":"P",
    "gn:feature_code":"PPL",
    "gn:name":"Sesedo",
    "gn:population":0,
    "gn:timezone":"Pacific/Guadalcanal",
    "iso:country":"SB",
    "wof:name":"Sesedo",
    "wof:placetype":"locality"
},
  "geometry": {"coordinates":[159.75708999999995,-8.48069],"type":"Point"}
}