{
  "type": "Feature",
  "properties": {
    "gn:admin1_code":"0.0",
    "gn:asciiname":"Mbetitambu",
    "gn:country_code":"SB",
    "gn:dem":460,
    "gn:feature_class":"P",
    "gn:feature_code":"PPL",
    "gn:name":"Mbetitambu",
    "gn:population":0,
    "gn:timezone":"Pacific/Guadalcanal",
    "iso:country":"SB",
    "wof:name":"Mbetitambu",
    "wof:placetype":"locality"
},
  "geometry": {"coordinates":[160.31863999999999,-9.60528],"type":"Point"}
}