{
  "type": "Feature",
  "properties": {
    "gn:admin1_code":"0.0",
    "gn:asciiname":"Fulitafe",
    "gn:country_code":"SB",
    "gn:dem":284,
    "gn:feature_class":"P",
    "gn:feature_code":"PPL",
    "gn:name":"Fulitafe",
    "gn:population":0,
    "gn:timezone":"Pacific/Guadalcanal",
    "iso:country":"SB",
    "wof:name":"Fulitafe",
    "wof:placetype":"locality"
},
  "geometry": {"coordinates":[160.73904999999999,-8.40307],"type":"Point"}
}