{
  "type": "Feature",
  "properties": {
    "gn:admin1_code":"0.0",
    "gn:asciiname":"Matahenua",
    "gn:country_code":"SB",
    "gn:dem":22,
    "gn:feature_class":"P",
    "gn:feature_code":"PPL",
    "gn:name":"Matahenua",
    "gn:population":0,
    "gn:timezone":"Pacific/Guadalcanal",
    "iso:country":"SB",
    "wof:name":"Matahenua",
    "wof:placetype":"locality"
},
  "geometry": {"coordinates":[159.78333000000001,-11.28333],"type":"Point"}
}