{
  "type": "Feature",
  "properties": {
    "gn:admin1_code":"0.0",
    "gn:asciiname":"Na Vura",
    "gn:country_code":"SB",
    "gn:dem":269,
    "gn:feature_class":"P",
    "gn:feature_code":"PPL",
    "gn:name":"Na Vura",
    "gn:population":0,
    "gn:timezone":"Pacific/Guadalcanal",
    "iso:country":"SB",
    "wof:name":"Na Vura",
    "wof:placetype":"locality"
},
  "geometry": {"coordinates":[160.71423999999999,-9.82016],"type":"Point"}
}