{
  "type": "Feature",
  "properties": {
    "gn:admin1_code":"0.0",
    "gn:asciiname":"Eleoteve",
    "gn:country_code":"SB",
    "gn:dem":8,
    "gn:feature_class":"P",
    "gn:feature_code":"PPL",
    "gn:name":"Eleoteve",
    "gn:population":0,
    "gn:timezone":"Pacific/Guadalcanal",
    "iso:country":"SB",
    "name:und_x_variant":[
        "Eliotavi",
        "Eleoteve"
    ],
    "wof:name":"Eleoteve",
    "wof:placetype":"locality"
},
  "geometry": {"coordinates":[156.72401000000005,-7.83086],"type":"Point"}
}