{
  "type": "Feature",
  "properties": {
    "gn:admin1_code":"0.0",
    "gn:asciiname":"Matavati",
    "gn:country_code":"SB",
    "gn:dem":182,
    "gn:feature_class":"P",
    "gn:feature_code":"PPL",
    "gn:name":"Matavati",
    "gn:population":0,
    "gn:timezone":"Pacific/Guadalcanal",
    "iso:country":"SB",
    "wof:name":"Matavati",
    "wof:placetype":"locality"
},
  "geometry": {"coordinates":[160.30909,-9.55889],"type":"Point"}
}