{
  "type": "Feature",
  "properties": {
    "gn:admin1_code":"0.0",
    "gn:asciiname":"Malisa",
    "gn:country_code":"SB",
    "gn:dem":323,
    "gn:feature_class":"P",
    "gn:feature_code":"PPL",
    "gn:name":"Malisa",
    "gn:population":0,
    "gn:timezone":"Pacific/Guadalcanal",
    "iso:country":"SB",
    "wof:name":"Malisa",
    "wof:placetype":"locality"
},
  "geometry": {"coordinates":[159.95415,-9.79709],"type":"Point"}
}