{
  "type": "Feature",
  "properties": {
    "gn:admin1_code":"0.0",
    "gn:asciiname":"Vunjimbuli",
    "gn:country_code":"SB",
    "gn:dem":501,
    "gn:feature_class":"P",
    "gn:feature_code":"PPL",
    "gn:name":"Vunjimbuli",
    "gn:population":0,
    "gn:timezone":"Pacific/Guadalcanal",
    "iso:country":"SB",
    "wof:name":"Vunjimbuli",
    "wof:placetype":"locality"
},
  "geometry": {"coordinates":[160.58938000000001,-9.75136],"type":"Point"}
}