{
  "type": "Feature",
  "properties": {
    "gn:admin1_code":"0.0",
    "gn:asciiname":"Sita",
    "gn:country_code":"SB",
    "gn:dem":84,
    "gn:feature_class":"P",
    "gn:feature_code":"PPL",
    "gn:name":"Sita",
    "gn:population":0,
    "gn:timezone":"Pacific/Guadalcanal",
    "iso:country":"SB",
    "wof:name":"Sita",
    "wof:placetype":"locality"
},
  "geometry": {"coordinates":[160.73586,-8.81754],"type":"Point"}
}