{
  "type": "Feature",
  "properties": {
    "gn:admin1_code":"0.0",
    "gn:asciiname":"Haa'apu",
    "gn:country_code":"SB",
    "gn:dem":53,
    "gn:feature_class":"P",
    "gn:feature_code":"PPL",
    "gn:name":"Haa\u2019apu",
    "gn:population":0,
    "gn:timezone":"Pacific/Guadalcanal",
    "iso:country":"SB",
    "wof:name":"Haa'apu",
    "wof:placetype":"locality"
},
  "geometry": {"coordinates":[161.03799999999995,-9.28605],"type":"Point"}
}