{
  "type": "Feature",
  "properties": {
    "gn:admin1_code":"0.0",
    "gn:asciiname":"Aroaro",
    "gn:country_code":"SB",
    "gn:dem":23,
    "gn:feature_class":"P",
    "gn:feature_code":"PPL",
    "gn:name":"Aroaro",
    "gn:population":0,
    "gn:timezone":"Pacific/Guadalcanal",
    "iso:country":"SB",
    "wof:name":"Aroaro",
    "wof:placetype":"locality"
},
  "geometry": {"coordinates":[160.05709999999999,-9.47599],"type":"Point"}
}