{
  "type": "Feature",
  "properties": {
    "gn:admin1_code":"0.0",
    "gn:asciiname":"Nggwauafa",
    "gn:country_code":"SB",
    "gn:dem":500,
    "gn:feature_class":"P",
    "gn:feature_code":"PPL",
    "gn:name":"Nggwauafa",
    "gn:population":0,
    "gn:timezone":"Pacific/Guadalcanal",
    "iso:country":"SB",
    "wof:name":"Nggwauafa",
    "wof:placetype":"locality"
},
  "geometry": {"coordinates":[160.69356999999999,-8.40631],"type":"Point"}
}