{
  "type": "Feature",
  "properties": {
    "gn:admin1_code":"0.0",
    "gn:asciiname":"Hapai",
    "gn:country_code":"SB",
    "gn:dem":15,
    "gn:feature_class":"P",
    "gn:feature_code":"PPL",
    "gn:name":"Hapai",
    "gn:population":0,
    "gn:timezone":"Pacific/Guadalcanal",
    "iso:country":"SB",
    "name:und_x_variant":[
        "Ghamburi",
        "Hapai"
    ],
    "wof:name":"Hapai",
    "wof:placetype":"locality"
},
  "geometry": {"coordinates":[157.56465,-8.29537],"type":"Point"}
}