{
  "type": "Feature",
  "properties": {
    "gn:admin1_code":"0.0",
    "gn:asciiname":"Mbisuana",
    "gn:country_code":"SB",
    "gn:dem":11,
    "gn:feature_class":"P",
    "gn:feature_code":"PPL",
    "gn:name":"Mbisuana",
    "gn:population":0,
    "gn:timezone":"Pacific/Guadalcanal",
    "iso:country":"SB",
    "wof:name":"Mbisuana",
    "wof:placetype":"locality"
},
  "geometry": {"coordinates":[158.10263999999995,-8.53194],"type":"Point"}
}