{
  "type": "Feature",
  "properties": {
    "gn:admin1_code":"0.0",
    "gn:asciiname":"Kakalao",
    "gn:country_code":"SB",
    "gn:dem":39,
    "gn:feature_class":"P",
    "gn:feature_code":"PPL",
    "gn:name":"Kakalao",
    "gn:population":0,
    "gn:timezone":"Pacific/Guadalcanal",
    "iso:country":"SB",
    "wof:name":"Kakalao",
    "wof:placetype":"locality"
},
  "geometry": {"coordinates":[160.27000000000001,-9.50079],"type":"Point"}
}