{
  "type": "Feature",
  "properties": {
    "gn:admin1_code":"0.0",
    "gn:asciiname":"Na Hambusi",
    "gn:country_code":"SB",
    "gn:dem":103,
    "gn:feature_class":"P",
    "gn:feature_code":"PPL",
    "gn:name":"Na Hambusi",
    "gn:population":0,
    "gn:timezone":"Pacific/Guadalcanal",
    "iso:country":"SB",
    "wof:name":"Na Hambusi",
    "wof:placetype":"locality"
},
  "geometry": {"coordinates":[160.23768000000001,-9.78787],"type":"Point"}
}