{
  "type": "Feature",
  "properties": {
    "gn:admin1_code":"0.0",
    "gn:asciiname":"Kopiu",
    "gn:country_code":"SB",
    "gn:dem":15,
    "gn:feature_class":"P",
    "gn:feature_code":"PPL",
    "gn:name":"Kopiu",
    "gn:population":0,
    "gn:timezone":"Pacific/Guadalcanal",
    "iso:country":"SB",
    "wof:name":"Kopiu",
    "wof:placetype":"locality"
},
  "geometry": {"coordinates":[160.78683999999996,-9.88219],"type":"Point"}
}