{
  "type": "Feature",
  "properties": {
    "gn:admin1_code":"0.0",
    "gn:asciiname":"Raria'oa",
    "gn:country_code":"SB",
    "gn:dem":5,
    "gn:feature_class":"P",
    "gn:feature_code":"PPL",
    "gn:name":"Raria\u2019oa",
    "gn:population":0,
    "gn:timezone":"Pacific/Guadalcanal",
    "iso:country":"SB",
    "wof:name":"Raria'oa",
    "wof:placetype":"locality"
},
  "geometry": {"coordinates":[161.19762,-9.15018],"type":"Point"}
}