{
  "type": "Feature",
  "properties": {
    "gn:admin1_code":"0.0",
    "gn:asciiname":"Paimbeta",
    "gn:country_code":"SB",
    "gn:dem":18,
    "gn:feature_class":"P",
    "gn:feature_code":"PPL",
    "gn:name":"Paimbeta",
    "gn:population":0,
    "gn:timezone":"Pacific/Guadalcanal",
    "iso:country":"SB",
    "wof:name":"Paimbeta",
    "wof:placetype":"locality"
},
  "geometry": {"coordinates":[159.83866,-9.12714],"type":"Point"}
}