{
  "type": "Feature",
  "properties": {
    "gn:admin1_code":"0.0",
    "gn:asciiname":"Nudungi",
    "gn:cc2":"SB",
    "gn:country_code":"SB",
    "gn:dem":1,
    "gn:feature_class":"P",
    "gn:feature_code":"PPL",
    "gn:name":"Nudungi",
    "gn:population":0,
    "gn:timezone":"Pacific/Guadalcanal",
    "iso:country":"SB",
    "name:und_x_variant":[
        "Nudung",
        "Nudungi"
    ],
    "wof:name":"Nudungi",
    "wof:placetype":"locality"
},
  "geometry": {"coordinates":[165.78333000000001,-10.71667],"type":"Point"}
}