{
  "type": "Feature",
  "properties": {
    "gn:admin1_code":"0.0",
    "gn:asciiname":"'Oofu",
    "gn:country_code":"SB",
    "gn:dem":15,
    "gn:feature_class":"P",
    "gn:feature_code":"PPL",
    "gn:name":"\u2019Oofu",
    "gn:population":0,
    "gn:timezone":"Pacific/Guadalcanal",
    "iso:country":"SB",
    "name:und_x_variant":[
        "\u2019Oofa",
        "\u2019Oofu"
    ],
    "wof:name":"'Oofu",
    "wof:placetype":"locality"
},
  "geometry": {"coordinates":[160.60398000000001,-8.41443],"type":"Point"}
}