{
  "type": "Feature",
  "properties": {
    "gn:admin1_code":"0.0",
    "gn:asciiname":"Alelua",
    "gn:country_code":"SB",
    "gn:dem":20,
    "gn:feature_class":"P",
    "gn:feature_code":"PPL",
    "gn:name":"Alelua",
    "gn:population":0,
    "gn:timezone":"Pacific/Guadalcanal",
    "iso:country":"SB",
    "wof:name":"Alelua",
    "wof:placetype":"locality"
},
  "geometry": {"coordinates":[160.94014999999999,-9.18317],"type":"Point"}
}