{
  "type": "Feature",
  "properties": {
    "gn:admin1_code":"0.0",
    "gn:asciiname":"Pasana",
    "gn:country_code":"SB",
    "gn:dem":5,
    "gn:feature_class":"P",
    "gn:feature_code":"PPL",
    "gn:name":"Pasana",
    "gn:population":0,
    "gn:timezone":"Pacific/Guadalcanal",
    "iso:country":"SB",
    "name:und_x_variant":[
        "Kaltoma",
        "Pasana"
    ],
    "wof:name":"Pasana",
    "wof:placetype":"locality"
},
  "geometry": {"coordinates":[159.71698000000001,-9.69058],"type":"Point"}
}