{
  "type": "Feature",
  "properties": {
    "gn:admin1_code":"0.0",
    "gn:asciiname":"Ke'ana",
    "gn:country_code":"SB",
    "gn:dem":-9999,
    "gn:feature_class":"P",
    "gn:feature_code":"PPL",
    "gn:name":"Ke\u2019ana",
    "gn:population":0,
    "gn:timezone":"Pacific/Guadalcanal",
    "iso:country":"SB",
    "wof:name":"Ke'ana",
    "wof:placetype":"locality"
},
  "geometry": {"coordinates":[161.16666999999995,-8.98333],"type":"Point"}
}