{
  "type": "Feature",
  "properties": {
    "gn:admin1_code":"0.0",
    "gn:asciiname":"Bungusile",
    "gn:country_code":"SB",
    "gn:dem":144,
    "gn:feature_class":"P",
    "gn:feature_code":"PPL",
    "gn:name":"Bungusile",
    "gn:population":0,
    "gn:timezone":"Pacific/Guadalcanal",
    "iso:country":"SB",
    "name:und_x_variant":[
        "Mbughulusule",
        "Bungusile"
    ],
    "wof:name":"Bungusile",
    "wof:placetype":"locality"
},
  "geometry": {"coordinates":[159.66363999999999,-8.50535],"type":"Point"}
}