{
  "type": "Feature",
  "properties": {
    "gn:admin1_code":"0.0",
    "gn:asciiname":"Koela",
    "gn:country_code":"SB",
    "gn:dem":25,
    "gn:feature_class":"P",
    "gn:feature_code":"PPL",
    "gn:name":"Koela",
    "gn:population":0,
    "gn:timezone":"Pacific/Guadalcanal",
    "iso:country":"SB",
    "name:deu_x_preferred":[
        "Koela"
    ],
    "name:est_x_preferred":[
        "Koela"
    ],
    "name:fra_x_preferred":[
        "Koela"
    ],
    "name:hye_x_preferred":[
        "\u053f\u0578\u0565\u056c\u0561"
    ],
    "name:nld_x_preferred":[
        "Koela"
    ],
    "name:pol_x_preferred":[
        "Koela"
    ],
    "name:spa_x_preferred":[
        "Koela"
    ],
    "name:ukr_x_preferred":[
        "\u041a\u043e\u0435\u043b\u0430"
    ],
    "name:vol_x_preferred":[
        "Koela"
    ],
    "wof:name":"Koela",
    "wof:placetype":"locality"
},
  "geometry": {"coordinates":[160.36778000000001,-9.48169],"type":"Point"}
}