{
  "type": "Feature",
  "properties": {
    "gn:admin1_code":"0.0",
    "gn:asciiname":"Mbokolovo",
    "gn:country_code":"SB",
    "gn:dem":12,
    "gn:feature_class":"P",
    "gn:feature_code":"PPL",
    "gn:name":"Mbokolovo",
    "gn:population":0,
    "gn:timezone":"Pacific/Guadalcanal",
    "iso:country":"SB",
    "wof:name":"Mbokolovo",
    "wof:placetype":"locality"
},
  "geometry": {"coordinates":[160.15472,-9.43165],"type":"Point"}
}