{
  "type": "Feature",
  "properties": {
    "gn:admin1_code":"0.0",
    "gn:asciiname":"Lungua",
    "gn:country_code":"SB",
    "gn:dem":46,
    "gn:feature_class":"P",
    "gn:feature_code":"PPL",
    "gn:name":"Lungua",
    "gn:population":0,
    "gn:timezone":"Pacific/Guadalcanal",
    "iso:country":"SB",
    "wof:name":"Lungua",
    "wof:placetype":"locality"
},
  "geometry": {"coordinates":[160.01667,-8.88333],"type":"Point"}
}