{
  "type": "Feature",
  "properties": {
    "gn:admin1_code":"0.0",
    "gn:asciiname":"U'uri",
    "gn:country_code":"SB",
    "gn:dem":75,
    "gn:feature_class":"P",
    "gn:feature_code":"PPL",
    "gn:name":"U\u2019uri",
    "gn:population":0,
    "gn:timezone":"Pacific/Guadalcanal",
    "iso:country":"SB",
    "wof:name":"U'uri",
    "wof:placetype":"locality"
},
  "geometry": {"coordinates":[159.64989,-8.19603],"type":"Point"}
}