{
  "type": "Feature",
  "properties": {
    "gn:admin1_code":"0.0",
    "gn:asciiname":"Fa'arau",
    "gn:country_code":"SB",
    "gn:dem":6,
    "gn:feature_class":"P",
    "gn:feature_code":"PPL",
    "gn:name":"Fa\u2019arau",
    "gn:population":0,
    "gn:timezone":"Pacific/Guadalcanal",
    "iso:country":"SB",
    "wof:name":"Fa'arau",
    "wof:placetype":"locality"
},
  "geometry": {"coordinates":[160.74376000000001,-8.85163],"type":"Point"}
}