{
  "type": "Feature",
  "properties": {
    "gn:admin1_code":"0.0",
    "gn:asciiname":"Fiu",
    "gn:country_code":"SB",
    "gn:dem":8,
    "gn:feature_class":"P",
    "gn:feature_code":"PPL",
    "gn:name":"Fiu",
    "gn:population":0,
    "gn:timezone":"Pacific/Guadalcanal",
    "iso:country":"SB",
    "name:und_x_variant":[
        "Fiu Mission",
        "Fiu"
    ],
    "wof:name":"Fiu",
    "wof:placetype":"locality"
},
  "geometry": {"coordinates":[160.70423,-8.72417],"type":"Point"}
}