{
  "type": "Feature",
  "properties": {
    "gn:admin1_code":"0.0",
    "gn:asciiname":"Mulusu",
    "gn:country_code":"SB",
    "gn:dem":74,
    "gn:feature_class":"P",
    "gn:feature_code":"PPL",
    "gn:name":"Mulusu",
    "gn:population":0,
    "gn:timezone":"Pacific/Guadalcanal",
    "iso:country":"SB",
    "wof:name":"Mulusu",
    "wof:placetype":"locality"
},
  "geometry": {"coordinates":[157.08918,-6.98417],"type":"Point"}
}