{
  "type": "Feature",
  "properties": {
    "gn:admin1_code":"0.0",
    "gn:asciiname":"Namonambosa",
    "gn:country_code":"SB",
    "gn:dem":329,
    "gn:feature_class":"P",
    "gn:feature_code":"PPL",
    "gn:name":"Namonambosa",
    "gn:population":0,
    "gn:timezone":"Pacific/Guadalcanal",
    "iso:country":"SB",
    "wof:name":"Namonambosa",
    "wof:placetype":"locality"
},
  "geometry": {"coordinates":[160.27191999999999,-9.67951],"type":"Point"}
}