{
  "type": "Feature",
  "properties": {
    "gn:admin1_code":"0.0",
    "gn:asciiname":"Ngalitaghaverona",
    "gn:country_code":"SB",
    "gn:dem":16,
    "gn:feature_class":"P",
    "gn:feature_code":"PPL",
    "gn:name":"Ngalitaghaverona",
    "gn:population":0,
    "gn:timezone":"Pacific/Guadalcanal",
    "iso:country":"SB",
    "wof:name":"Ngalitaghaverona",
    "wof:placetype":"locality"
},
  "geometry": {"coordinates":[160.22803000000005,-9.80924],"type":"Point"}
}