{
  "type": "Feature",
  "properties": {
    "gn:admin1_code":"0.0",
    "gn:asciiname":"Naghatare",
    "gn:country_code":"SB",
    "gn:dem":297,
    "gn:feature_class":"P",
    "gn:feature_code":"PPL",
    "gn:name":"Naghatare",
    "gn:population":0,
    "gn:timezone":"Pacific/Guadalcanal",
    "iso:country":"SB",
    "name:und_x_variant":[
        "Ngagatari",
        "Naghatare"
    ],
    "wof:name":"Naghatare",
    "wof:placetype":"locality"
},
  "geometry": {"coordinates":[162.11139,-10.54271],"type":"Point"}
}