{
  "type": "Feature",
  "properties": {
    "gn:admin1_code":"0.0",
    "gn:asciiname":"Verakelia",
    "gn:country_code":"SB",
    "gn:dem":875,
    "gn:feature_class":"P",
    "gn:feature_code":"PPL",
    "gn:name":"Verakelia",
    "gn:population":0,
    "gn:timezone":"Pacific/Guadalcanal",
    "iso:country":"SB",
    "wof:name":"Verakelia",
    "wof:placetype":"locality"
},
  "geometry": {"coordinates":[160.34999999999999,-9.73333],"type":"Point"}
}