{
  "type": "Feature",
  "properties": {
    "gn:admin1_code":"0.0",
    "gn:asciiname":"Saira",
    "gn:country_code":"SB",
    "gn:dem":19,
    "gn:feature_class":"P",
    "gn:feature_code":"PPL",
    "gn:name":"Saira",
    "gn:population":0,
    "gn:timezone":"Pacific/Guadalcanal",
    "iso:country":"SB",
    "name:deu_x_preferred":[
        "Saira"
    ],
    "name:nds_x_preferred":[
        "Saira"
    ],
    "wof:name":"Saira",
    "wof:placetype":"locality"
},
  "geometry": {"coordinates":[157.98374999999999,-8.76194],"type":"Point"}
}