{
  "type": "Feature",
  "properties": {
    "gn:admin1_code":"0.0",
    "gn:asciiname":"Maro'umasike",
    "gn:country_code":"SB",
    "gn:dem":6,
    "gn:feature_class":"P",
    "gn:feature_code":"PPL",
    "gn:name":"Maro\u2019umasike",
    "gn:population":0,
    "gn:timezone":"Pacific/Guadalcanal",
    "iso:country":"SB",
    "wof:name":"Maro'umasike",
    "wof:placetype":"locality"
},
  "geometry": {"coordinates":[161.24201000000005,-9.31953],"type":"Point"}
}