{
  "type": "Feature",
  "properties": {
    "gn:admin1_code":"0.0",
    "gn:asciiname":"Taora",
    "gn:country_code":"SB",
    "gn:dem":4,
    "gn:feature_class":"P",
    "gn:feature_code":"PPL",
    "gn:name":"Taora",
    "gn:population":0,
    "gn:timezone":"Pacific/Guadalcanal",
    "iso:country":"SB",
    "wof:name":"Taora",
    "wof:placetype":"locality"
},
  "geometry": {"coordinates":[157.48951,-7.40484],"type":"Point"}
}