{
  "type": "Feature",
  "properties": {
    "gn:admin1_code":"0.0",
    "gn:asciiname":"Raunitono",
    "gn:country_code":"SB",
    "gn:dem":1,
    "gn:feature_class":"P",
    "gn:feature_code":"PPL",
    "gn:name":"Raunitono",
    "gn:population":0,
    "gn:timezone":"Pacific/Guadalcanal",
    "iso:country":"SB",
    "wof:name":"Raunitono",
    "wof:placetype":"locality"
},
  "geometry": {"coordinates":[160.84173000000001,-9.84045],"type":"Point"}
}