{
  "type": "Feature",
  "properties": {
    "gn:admin1_code":"0.0",
    "gn:asciiname":"Balasu'u",
    "gn:country_code":"SB",
    "gn:dem":-9999,
    "gn:feature_class":"P",
    "gn:feature_code":"PPL",
    "gn:name":"Balasu\u2019u",
    "gn:population":0,
    "gn:timezone":"Pacific/Guadalcanal",
    "iso:country":"SB",
    "wof:name":"Balasu'u",
    "wof:placetype":"locality"
},
  "geometry": {"coordinates":[161.55000000000001,-9.56667],"type":"Point"}
}