{
  "type": "Feature",
  "properties": {
    "gn:admin1_code":"0.0",
    "gn:asciiname":"Naonuli",
    "gn:cc2":"SB",
    "gn:country_code":"SB",
    "gn:dem":13,
    "gn:feature_class":"P",
    "gn:feature_code":"PPL",
    "gn:name":"Naonuli",
    "gn:population":0,
    "gn:timezone":"Pacific/Guadalcanal",
    "iso:country":"SB",
    "name:und_x_variant":[
        "Naonauli",
        "Naonuli"
    ],
    "wof:name":"Naonuli",
    "wof:placetype":"locality"
},
  "geometry": {"coordinates":[160.93333000000001,-8.78333],"type":"Point"}
}