{
  "type": "Feature",
  "properties": {
    "gn:admin1_code":"8.0",
    "gn:asciiname":"Umara Village",
    "gn:country_code":"SB",
    "gn:dem":12,
    "gn:feature_class":"P",
    "gn:feature_code":"PPL",
    "gn:name":"Umara Village",
    "gn:population":0,
    "gn:timezone":"Pacific/Guadalcanal",
    "iso:country":"SB",
    "name:und_x_variant":[
        "Umara",
        "Pa\u2019epa\u2019esahuhu"
    ],
    "wof:name":"Umara Village",
    "wof:placetype":"locality"
},
  "geometry": {"coordinates":[161.70658,-10.24812],"type":"Point"}
}