{
  "type": "Feature",
  "properties": {
    "gn:admin1_code":"0.0",
    "gn:asciiname":"Ane'efafako",
    "gn:country_code":"SB",
    "gn:dem":705,
    "gn:feature_class":"P",
    "gn:feature_code":"PPL",
    "gn:name":"Ane\u2019efafako",
    "gn:population":0,
    "gn:timezone":"Pacific/Guadalcanal",
    "iso:country":"SB",
    "wof:name":"Ane'efafako",
    "wof:placetype":"locality"
},
  "geometry": {"coordinates":[161.04418999999999,-8.9262],"type":"Point"}
}