{
  "type": "Feature",
  "properties": {
    "gn:admin1_code":"0.0",
    "gn:asciiname":"Hara'ina",
    "gn:country_code":"SB",
    "gn:dem":7,
    "gn:feature_class":"P",
    "gn:feature_code":"PPL",
    "gn:name":"Hara\u2019ina",
    "gn:population":0,
    "gn:timezone":"Pacific/Guadalcanal",
    "iso:country":"SB",
    "wof:name":"Hara'ina",
    "wof:placetype":"locality"
},
  "geometry": {"coordinates":[161.96088,-9.72141],"type":"Point"}
}