{
  "type": "Feature",
  "properties": {
    "gn:admin1_code":"0.0",
    "gn:asciiname":"Kalenga",
    "gn:country_code":"SB",
    "gn:dem":15,
    "gn:feature_class":"P",
    "gn:feature_code":"PPL",
    "gn:name":"Kalenga",
    "gn:population":0,
    "gn:timezone":"Pacific/Guadalcanal",
    "iso:country":"SB",
    "name:ita_x_preferred":[
        "Kalenga"
    ],
    "name:swa_x_preferred":[
        "Kalenga"
    ],
    "wof:name":"Kalenga",
    "wof:placetype":"locality"
},
  "geometry": {"coordinates":[159.83566000000005,-8.55135],"type":"Point"}
}