{
  "type": "Feature",
  "properties": {
    "gn:admin1_code":"0.0",
    "gn:asciiname":"Bwaunasughu",
    "gn:country_code":"SB",
    "gn:dem":33,
    "gn:feature_class":"P",
    "gn:feature_code":"PPL",
    "gn:name":"Bwaunasughu",
    "gn:population":0,
    "gn:timezone":"Pacific/Guadalcanal",
    "iso:country":"SB",
    "name:und_x_variant":[
        "Bwaunasu\u2019u",
        "Bwaunasughu"
    ],
    "wof:name":"Bwaunasughu",
    "wof:placetype":"locality"
},
  "geometry": {"coordinates":[161.91727,-10.46047],"type":"Point"}
}