{
  "type": "Feature",
  "properties": {
    "gn:admin1_code":"0.0",
    "gn:asciiname":"Naufee",
    "gn:country_code":"SB",
    "gn:dem":543,
    "gn:feature_class":"P",
    "gn:feature_code":"PPL",
    "gn:name":"Naufee",
    "gn:population":0,
    "gn:timezone":"Pacific/Guadalcanal",
    "iso:country":"SB",
    "wof:name":"Naufee",
    "wof:placetype":"locality"
},
  "geometry": {"coordinates":[161.06221000000005,-8.92593],"type":"Point"}
}