{
  "type": "Feature",
  "properties": {
    "gn:admin1_code":"0.0",
    "gn:asciiname":"Fauketa",
    "gn:country_code":"SB",
    "gn:dem":509,
    "gn:feature_class":"P",
    "gn:feature_code":"PPL",
    "gn:name":"Fauketa",
    "gn:population":0,
    "gn:timezone":"Pacific/Guadalcanal",
    "iso:country":"SB",
    "wof:name":"Fauketa",
    "wof:placetype":"locality"
},
  "geometry": {"coordinates":[160.84971999999999,-8.74379],"type":"Point"}
}