{
  "type": "Feature",
  "properties": {
    "gn:admin1_code":"0.0",
    "gn:asciiname":"Fouambu",
    "gn:country_code":"SB",
    "gn:dem":37,
    "gn:feature_class":"P",
    "gn:feature_code":"PPL",
    "gn:name":"Fouambu",
    "gn:population":0,
    "gn:timezone":"Pacific/Guadalcanal",
    "iso:country":"SB",
    "wof:name":"Fouambu",
    "wof:placetype":"locality"
},
  "geometry": {"coordinates":[160.80114,-8.40655],"type":"Point"}
}