{
  "type": "Feature",
  "properties": {
    "gn:admin1_code":"0.0",
    "gn:asciiname":"Komunimboko",
    "gn:country_code":"SB",
    "gn:dem":7,
    "gn:feature_class":"P",
    "gn:feature_code":"PPL",
    "gn:name":"Komunimboko",
    "gn:population":0,
    "gn:timezone":"Pacific/Guadalcanal",
    "iso:country":"SB",
    "wof:name":"Komunimboko",
    "wof:placetype":"locality"
},
  "geometry": {"coordinates":[160.49249,-9.5372],"type":"Point"}
}