{
  "type": "Feature",
  "properties": {
    "gn:admin1_code":"0.0",
    "gn:asciiname":"Mbumbughoro",
    "gn:country_code":"SB",
    "gn:dem":455,
    "gn:feature_class":"P",
    "gn:feature_code":"PPL",
    "gn:name":"Mbumbughoro",
    "gn:population":0,
    "gn:timezone":"Pacific/Guadalcanal",
    "iso:country":"SB",
    "name:und_x_variant":[
        "Bumbugaro",
        "Bumbugoro",
        "Mbumbughoro"
    ],
    "wof:name":"Mbumbughoro",
    "wof:placetype":"locality"
},
  "geometry": {"coordinates":[160.32504,-9.60415],"type":"Point"}
}