{
  "type": "Feature",
  "properties": {
    "gn:admin1_code":"0.0",
    "gn:asciiname":"Anofalake",
    "gn:country_code":"SB",
    "gn:dem":376,
    "gn:feature_class":"P",
    "gn:feature_code":"PPL",
    "gn:name":"Anofalake",
    "gn:population":0,
    "gn:timezone":"Pacific/Guadalcanal",
    "iso:country":"SB",
    "wof:name":"Anofalake",
    "wof:placetype":"locality"
},
  "geometry": {"coordinates":[160.72486000000001,-8.65691],"type":"Point"}
}