{
  "type": "Feature",
  "properties": {
    "gn:admin1_code":"0.0",
    "gn:asciiname":"Rongokwere",
    "gn:country_code":"SB",
    "gn:dem":340,
    "gn:feature_class":"P",
    "gn:feature_code":"PPL",
    "gn:name":"Rongokwere",
    "gn:population":0,
    "gn:timezone":"Pacific/Guadalcanal",
    "iso:country":"SB",
    "wof:name":"Rongokwere",
    "wof:placetype":"locality"
},
  "geometry": {"coordinates":[160.86667,-8.53333],"type":"Point"}
}