{
  "type": "Feature",
  "properties": {
    "gn:admin1_code":"0.0",
    "gn:asciiname":"Soghati",
    "gn:country_code":"SB",
    "gn:dem":36,
    "gn:feature_class":"P",
    "gn:feature_code":"PPL",
    "gn:name":"Soghati",
    "gn:population":0,
    "gn:timezone":"Pacific/Guadalcanal",
    "iso:country":"SB",
    "name:fas_x_preferred":[
        "\u0633\u0648\u063a\u0627\u062a\u06cc"
    ],
    "wof:name":"Soghati",
    "wof:placetype":"locality"
},
  "geometry": {"coordinates":[159.71941000000001,-9.59953],"type":"Point"}
}