{
  "type": "Feature",
  "properties": {
    "gn:admin1_code":"0.0",
    "gn:asciiname":"Suilonggolonggo",
    "gn:country_code":"SB",
    "gn:dem":935,
    "gn:feature_class":"P",
    "gn:feature_code":"PPL",
    "gn:name":"Suilonggolonggo",
    "gn:population":0,
    "gn:timezone":"Pacific/Guadalcanal",
    "iso:country":"SB",
    "wof:name":"Suilonggolonggo",
    "wof:placetype":"locality"
},
  "geometry": {"coordinates":[160.35480999999999,-9.72681],"type":"Point"}
}