{
  "type": "Feature",
  "properties": {
    "gn:admin1_code":"13.0",
    "gn:asciiname":"Lavanggu",
    "gn:country_code":"SB",
    "gn:dem":68,
    "gn:feature_class":"P",
    "gn:feature_code":"PPL",
    "gn:name":"Lavanggu",
    "gn:population":0,
    "gn:timezone":"Pacific/Guadalcanal",
    "iso:country":"SB",
    "wof:name":"Lavanggu",
    "wof:placetype":"locality"
},
  "geometry": {"coordinates":[160.28016000000005,-11.65602],"type":"Point"}
}