{
  "type": "Feature",
  "properties": {
    "gn:admin1_code":"0.0",
    "gn:asciiname":"Tawarogha",
    "gn:country_code":"SB",
    "gn:dem":14,
    "gn:feature_class":"P",
    "gn:feature_code":"PPL",
    "gn:name":"Tawarogha",
    "gn:population":0,
    "gn:timezone":"Pacific/Guadalcanal",
    "iso:country":"SB",
    "name:und_x_variant":[
        "Tawaroga",
        "Tawarogha"
    ],
    "wof:name":"Tawarogha",
    "wof:placetype":"locality"
},
  "geometry": {"coordinates":[162.27105,-10.73863],"type":"Point"}
}