{
  "type": "Feature",
  "properties": {
    "gn:admin1_code":"0.0",
    "gn:asciiname":"Au'alu",
    "gn:country_code":"SB",
    "gn:dem":73,
    "gn:feature_class":"P",
    "gn:feature_code":"PPL",
    "gn:name":"Au\u2019alu",
    "gn:population":0,
    "gn:timezone":"Pacific/Guadalcanal",
    "iso:country":"SB",
    "wof:name":"Au'alu",
    "wof:placetype":"locality"
},
  "geometry": {"coordinates":[159.55262999999999,-8.27809],"type":"Point"}
}