{
  "type": "Feature",
  "properties": {
    "gn:admin1_code":"0.0",
    "gn:asciiname":"Namo'ia",
    "gn:country_code":"SB",
    "gn:dem":20,
    "gn:feature_class":"P",
    "gn:feature_code":"PPL",
    "gn:name":"Namo\u2019ia",
    "gn:population":0,
    "gn:timezone":"Pacific/Guadalcanal",
    "iso:country":"SB",
    "wof:name":"Namo'ia",
    "wof:placetype":"locality"
},
  "geometry": {"coordinates":[160.89738,-8.85155],"type":"Point"}
}