{
  "type": "Feature",
  "properties": {
    "gn:admin1_code":"0.0",
    "gn:asciiname":"Laloato",
    "gn:country_code":"SB",
    "gn:dem":12,
    "gn:feature_class":"P",
    "gn:feature_code":"PPL",
    "gn:name":"Laloato",
    "gn:population":0,
    "gn:timezone":"Pacific/Guadalcanal",
    "iso:country":"SB",
    "wof:name":"Laloato",
    "wof:placetype":"locality"
},
  "geometry": {"coordinates":[160.24467000000001,-9.80846],"type":"Point"}
}