{
  "type": "Feature",
  "properties": {
    "gn:admin1_code":"0.0",
    "gn:asciiname":"T'holana",
    "gn:country_code":"SB",
    "gn:dem":42,
    "gn:feature_class":"P",
    "gn:feature_code":"PPL",
    "gn:name":"T\u2019holana",
    "gn:population":0,
    "gn:timezone":"Pacific/Guadalcanal",
    "iso:country":"SB",
    "wof:name":"T'holana",
    "wof:placetype":"locality"
},
  "geometry": {"coordinates":[159.62537,-8.16417],"type":"Point"}
}