{
  "type": "Feature",
  "properties": {
    "gn:admin1_code":"0.0",
    "gn:asciiname":"Suramane",
    "gn:country_code":"SB",
    "gn:dem":34,
    "gn:feature_class":"P",
    "gn:feature_code":"PPL",
    "gn:name":"Suramane",
    "gn:population":0,
    "gn:timezone":"Pacific/Guadalcanal",
    "iso:country":"SB",
    "wof:name":"Suramane",
    "wof:placetype":"locality"
},
  "geometry": {"coordinates":[161.08333000000005,-9.28333],"type":"Point"}
}