{
  "type": "Feature",
  "properties": {
    "gn:admin1_code":"0.0",
    "gn:asciiname":"Ko'ombaita",
    "gn:country_code":"SB",
    "gn:dem":254,
    "gn:feature_class":"P",
    "gn:feature_code":"PPL",
    "gn:name":"Ko\u2019ombaita",
    "gn:population":0,
    "gn:timezone":"Pacific/Guadalcanal",
    "iso:country":"SB",
    "wof:name":"Ko'ombaita",
    "wof:placetype":"locality"
},
  "geometry": {"coordinates":[160.77393000000001,-8.41754],"type":"Point"}
}