{
  "type": "Feature",
  "properties": {
    "gn:admin1_code":"0.0",
    "gn:asciiname":"Rongofangaa",
    "gn:country_code":"SB",
    "gn:dem":105,
    "gn:feature_class":"P",
    "gn:feature_code":"PPL",
    "gn:name":"Rongofangaa",
    "gn:population":0,
    "gn:timezone":"Pacific/Guadalcanal",
    "iso:country":"SB",
    "wof:name":"Rongofangaa",
    "wof:placetype":"locality"
},
  "geometry": {"coordinates":[160.94999999999999,-8.66667],"type":"Point"}
}