{
  "type": "Feature",
  "properties": {
    "gn:admin1_code":"0.0",
    "gn:asciiname":"Kusumba",
    "gn:country_code":"SB",
    "gn:dem":226,
    "gn:feature_class":"P",
    "gn:feature_code":"PPL",
    "gn:name":"Kusumba",
    "gn:population":0,
    "gn:timezone":"Pacific/Guadalcanal",
    "iso:country":"SB",
    "wof:name":"Kusumba",
    "wof:placetype":"locality"
},
  "geometry": {"coordinates":[159.70975000000001,-9.58993],"type":"Point"}
}