{
  "type": "Feature",
  "properties": {
    "gn:admin1_code":"0.0",
    "gn:asciiname":"Malalaia",
    "gn:country_code":"SB",
    "gn:dem":950,
    "gn:feature_class":"P",
    "gn:feature_code":"PPL",
    "gn:name":"Malalaia",
    "gn:population":0,
    "gn:timezone":"Pacific/Guadalcanal",
    "iso:country":"SB",
    "wof:name":"Malalaia",
    "wof:placetype":"locality"
},
  "geometry": {"coordinates":[161.01196999999999,-8.94839],"type":"Point"}
}