{
  "type": "Feature",
  "properties": {
    "gn:admin1_code":"0.0",
    "gn:asciiname":"Karu'uu",
    "gn:country_code":"SB",
    "gn:dem":18,
    "gn:feature_class":"P",
    "gn:feature_code":"PPL",
    "gn:name":"Karu\u2019uu",
    "gn:population":0,
    "gn:timezone":"Pacific/Guadalcanal",
    "iso:country":"SB",
    "wof:name":"Karu'uu",
    "wof:placetype":"locality"
},
  "geometry": {"coordinates":[161.40676999999999,-9.46934],"type":"Point"}
}