{
  "type": "Feature",
  "properties": {
    "gn:admin1_code":"0.0",
    "gn:asciiname":"Inakona",
    "gn:country_code":"SB",
    "gn:dem":17,
    "gn:feature_class":"P",
    "gn:feature_code":"PPL",
    "gn:name":"Inakona",
    "gn:population":0,
    "gn:timezone":"Pacific/Guadalcanal",
    "iso:country":"SB",
    "name:und_x_variant":[
        "Inakona Mission",
        "Inakona"
    ],
    "wof:name":"Inakona",
    "wof:placetype":"locality"
},
  "geometry": {"coordinates":[160.04057,-9.82047],"type":"Point"}
}