{
  "type": "Feature",
  "properties": {
    "gn:admin1_code":"0.0",
    "gn:asciiname":"Valemanu",
    "gn:country_code":"SB",
    "gn:dem":-9999,
    "gn:feature_class":"P",
    "gn:feature_code":"PPL",
    "gn:name":"Valemanu",
    "gn:population":0,
    "gn:timezone":"Pacific/Guadalcanal",
    "iso:country":"SB",
    "wof:name":"Valemanu",
    "wof:placetype":"locality"
},
  "geometry": {"coordinates":[159.83243999999999,-9.15047],"type":"Point"}
}