{
  "type": "Feature",
  "properties": {
    "gn:admin1_code":"0.0",
    "gn:asciiname":"Andandaiesi",
    "gn:country_code":"SB",
    "gn:dem":47,
    "gn:feature_class":"P",
    "gn:feature_code":"PPL",
    "gn:name":"Andandaiesi",
    "gn:population":0,
    "gn:timezone":"Pacific/Guadalcanal",
    "iso:country":"SB",
    "wof:name":"Andandaiesi",
    "wof:placetype":"locality"
},
  "geometry": {"coordinates":[160.58822000000001,-8.33389],"type":"Point"}
}