{
  "type": "Feature",
  "properties": {
    "gn:admin1_code":"0.0",
    "gn:asciiname":"Aringa Hill",
    "gn:country_code":"SB",
    "gn:dem":1000,
    "gn:feature_class":"P",
    "gn:feature_code":"PPL",
    "gn:name":"Aringa Hill",
    "gn:population":0,
    "gn:timezone":"Pacific/Guadalcanal",
    "iso:country":"SB",
    "wof:name":"Aringa Hill",
    "wof:placetype":"locality"
},
  "geometry": {"coordinates":[160.96988000000005,-9.10747],"type":"Point"}
}