{
  "type": "Feature",
  "properties": {
    "gn:admin1_code":"0.0",
    "gn:asciiname":"Rongomoli",
    "gn:country_code":"SB",
    "gn:dem":398,
    "gn:feature_class":"P",
    "gn:feature_code":"PPL",
    "gn:name":"Rongomoli",
    "gn:population":0,
    "gn:timezone":"Pacific/Guadalcanal",
    "iso:country":"SB",
    "wof:name":"Rongomoli",
    "wof:placetype":"locality"
},
  "geometry": {"coordinates":[160.18348,-9.80257],"type":"Point"}
}