{
  "type": "Feature",
  "properties": {
    "gn:admin1_code":"0.0",
    "gn:asciiname":"Vatuteko",
    "gn:country_code":"SB",
    "gn:dem":43,
    "gn:feature_class":"P",
    "gn:feature_code":"PPL",
    "gn:name":"Vatuteko",
    "gn:population":0,
    "gn:timezone":"Pacific/Guadalcanal",
    "iso:country":"SB",
    "wof:name":"Vatuteko",
    "wof:placetype":"locality"
},
  "geometry": {"coordinates":[159.77793,-9.70683],"type":"Point"}
}