{
  "type": "Feature",
  "properties": {
    "gn:admin1_code":"0.0",
    "gn:asciiname":"Valasi",
    "gn:country_code":"SB",
    "gn:dem":133,
    "gn:feature_class":"P",
    "gn:feature_code":"PPL",
    "gn:name":"Valasi",
    "gn:population":0,
    "gn:timezone":"Pacific/Guadalcanal",
    "iso:country":"SB",
    "wof:name":"Valasi",
    "wof:placetype":"locality"
},
  "geometry": {"coordinates":[160.53575000000001,-9.65799],"type":"Point"}
}