{
  "type": "Feature",
  "properties": {
    "gn:admin1_code":"0.0",
    "gn:asciiname":"Amboiosi",
    "gn:country_code":"SB",
    "gn:dem":658,
    "gn:feature_class":"P",
    "gn:feature_code":"PPL",
    "gn:name":"Amboiosi",
    "gn:population":0,
    "gn:timezone":"Pacific/Guadalcanal",
    "iso:country":"SB",
    "wof:name":"Amboiosi",
    "wof:placetype":"locality"
},
  "geometry": {"coordinates":[161.01667,-8.91667],"type":"Point"}
}