{
  "type": "Feature",
  "properties": {
    "gn:admin1_code":"0.0",
    "gn:asciiname":"Polo",
    "gn:country_code":"SB",
    "gn:dem":9,
    "gn:feature_class":"P",
    "gn:feature_code":"PPL",
    "gn:name":"Polo",
    "gn:population":0,
    "gn:timezone":"Pacific/Guadalcanal",
    "iso:country":"SB",
    "wof:name":"Polo",
    "wof:placetype":"locality"
},
  "geometry": {"coordinates":[156.65115,-6.6864],"type":"Point"}
}