{
  "type": "Feature",
  "properties": {
    "gn:admin1_code":"0.0",
    "gn:asciiname":"'Ere'eresulu",
    "gn:country_code":"SB",
    "gn:dem":359,
    "gn:feature_class":"P",
    "gn:feature_code":"PPL",
    "gn:name":"\u2019Ere\u2019eresulu",
    "gn:population":0,
    "gn:timezone":"Pacific/Guadalcanal",
    "iso:country":"SB",
    "name:und_x_variant":[
        "\u2019Ere Amsuli",
        "\u2019Ere\u2019eresulu"
    ],
    "wof:name":"'Ere'eresulu",
    "wof:placetype":"locality"
},
  "geometry": {"coordinates":[160.75753999999995,-8.77678],"type":"Point"}
}