{
  "type": "Feature",
  "properties": {
    "gn:admin1_code":"0.0",
    "gn:asciiname":"Tawahaule",
    "gn:country_code":"SB",
    "gn:dem":13,
    "gn:feature_class":"P",
    "gn:feature_code":"PPL",
    "gn:name":"Tawahaule",
    "gn:population":0,
    "gn:timezone":"Pacific/Guadalcanal",
    "iso:country":"SB",
    "wof:name":"Tawahaule",
    "wof:placetype":"locality"
},
  "geometry": {"coordinates":[161.50753,-9.66193],"type":"Point"}
}