{
  "type": "Feature",
  "properties": {
    "gn:admin1_code":"0.0",
    "gn:asciiname":"Gounatolo",
    "gn:country_code":"SB",
    "gn:dem":15,
    "gn:feature_class":"P",
    "gn:feature_code":"PPL",
    "gn:name":"Gounatolo",
    "gn:population":0,
    "gn:timezone":"Pacific/Guadalcanal",
    "iso:country":"SB",
    "wof:name":"Gounatolo",
    "wof:placetype":"locality"
},
  "geometry": {"coordinates":[160.83921999999995,-8.45485],"type":"Point"}
}