{
  "type": "Feature",
  "properties": {
    "gn:admin1_code":"0.0",
    "gn:asciiname":"Oi'eke",
    "gn:country_code":"SB",
    "gn:dem":187,
    "gn:feature_class":"P",
    "gn:feature_code":"PPL",
    "gn:name":"Oi\u2019eke",
    "gn:population":0,
    "gn:timezone":"Pacific/Guadalcanal",
    "iso:country":"SB",
    "wof:name":"Oi'eke",
    "wof:placetype":"locality"
},
  "geometry": {"coordinates":[161.22048000000001,-9.17524],"type":"Point"}
}