{
  "type": "Feature",
  "properties": {
    "gn:admin1_code":"0.0",
    "gn:asciiname":"Rove",
    "gn:country_code":"SB",
    "gn:dem":21,
    "gn:feature_class":"P",
    "gn:feature_code":"PPL",
    "gn:name":"Rove",
    "gn:population":0,
    "gn:timezone":"Pacific/Guadalcanal",
    "iso:country":"SB",
    "name:bos_x_preferred":[
        "Rove"
    ],
    "name:ceb_x_preferred":[
        "Rove"
    ],
    "name:deu_x_preferred":[
        "Rove"
    ],
    "name:fra_x_preferred":[
        "Rove"
    ],
    "name:heb_x_preferred":[
        "\u05e8\u05d5\u05d1"
    ],
    "name:hrv_x_preferred":[
        "Rove"
    ],
    "name:nld_x_preferred":[
        "Rove"
    ],
    "name:rus_x_preferred":[
        "\u0420\u043e\u0443\u0432"
    ],
    "name:slv_x_preferred":[
        "Rove"
    ],
    "name:und_x_variant":[
        "Rova",
        "Rove"
    ],
    "wof:name":"Rove",
    "wof:placetype":"locality"
},
  "geometry": {"coordinates":[160.21428999999995,-9.08252],"type":"Point"}
}