{
  "type": "Feature",
  "properties": {
    "gn:admin1_code":"0.0",
    "gn:asciiname":"Rove",
    "gn:country_code":"SB",
    "gn:dem":21,
    "gn:feature_class":"P",
    "gn:feature_code":"PPL",
    "gn:name":"Rove",
    "gn:population":0,
    "gn:timezone":"Pacific/Guadalcanal",
    "iso:country":"SB",
    "name:und_x_variant":[
        "Rova",
        "Rove"
    ],
    "wof:name":"Rove",
    "wof:placetype":"locality"
},
  "geometry": {"coordinates":[160.21428999999995,-9.08252],"type":"Point"}
}