{
  "type": "Feature",
  "properties": {
    "gn:admin1_code":"0.0",
    "gn:asciiname":"Allardyce",
    "gn:country_code":"SB",
    "gn:dem":46,
    "gn:feature_class":"P",
    "gn:feature_code":"PPL",
    "gn:name":"Allardyce",
    "gn:population":0,
    "gn:timezone":"Pacific/Guadalcanal",
    "iso:country":"SB",
    "wof:name":"Allardyce",
    "wof:placetype":"locality"
},
  "geometry": {"coordinates":[158.66138000000001,-7.77845],"type":"Point"}
}