{
  "type": "Feature",
  "properties": {
    "gn:admin1_code":"0.0",
    "gn:asciiname":"Newland",
    "gn:country_code":"SB",
    "gn:dem":5,
    "gn:feature_class":"P",
    "gn:feature_code":"PPL",
    "gn:name":"Newland",
    "gn:population":0,
    "gn:timezone":"Pacific/Guadalcanal",
    "iso:country":"SB",
    "name:ceb_x_preferred":[
        "Newland"
    ],
    "name:deu_x_preferred":[
        "Newland"
    ],
    "name:fas_x_preferred":[
        "\u0646\u06cc\u0648\u0644\u0646\u062f"
    ],
    "name:fra_x_preferred":[
        "Newland"
    ],
    "name:ita_x_preferred":[
        "Newland"
    ],
    "name:nld_x_preferred":[
        "Newland"
    ],
    "name:pol_x_preferred":[
        "Newland"
    ],
    "name:rus_x_preferred":[
        "\u041d\u044c\u044e\u043b\u0435\u043d\u0434"
    ],
    "name:swe_x_preferred":[
        "Newland"
    ],
    "wof:name":"Newland",
    "wof:placetype":"locality"
},
  "geometry": {"coordinates":[157.82565,-8.56664],"type":"Point"}
}