{
  "type": "Feature",
  "properties": {
    "gn:admin1_code":"0.0",
    "gn:asciiname":"Newland",
    "gn:country_code":"SB",
    "gn:dem":5,
    "gn:feature_class":"P",
    "gn:feature_code":"PPL",
    "gn:name":"Newland",
    "gn:population":0,
    "gn:timezone":"Pacific/Guadalcanal",
    "iso:country":"SB",
    "wof:name":"Newland",
    "wof:placetype":"locality"
},
  "geometry": {"coordinates":[157.82565,-8.56664],"type":"Point"}
}