{
  "type": "Feature",
  "properties": {
    "gn:admin1_code":"0.0",
    "gn:asciiname":"Poroporo",
    "gn:country_code":"SB",
    "gn:dem":13,
    "gn:feature_class":"P",
    "gn:feature_code":"PPL",
    "gn:name":"Poroporo",
    "gn:population":0,
    "gn:timezone":"Pacific/Guadalcanal",
    "iso:country":"SB",
    "name:und_x_variant":[
        "Porapora",
        "Poroporo"
    ],
    "wof:name":"Poroporo",
    "wof:placetype":"locality"
},
  "geometry": {"coordinates":[156.39725000000001,-6.66141],"type":"Point"}
}