{
  "type": "Feature",
  "properties": {
    "gn:admin1_code":"0.0",
    "gn:asciiname":"Heuhonu",
    "gn:country_code":"SB",
    "gn:dem":122,
    "gn:feature_class":"P",
    "gn:feature_code":"PPL",
    "gn:name":"Heuhonu",
    "gn:population":0,
    "gn:timezone":"Pacific/Guadalcanal",
    "iso:country":"SB",
    "wof:name":"Heuhonu",
    "wof:placetype":"locality"
},
  "geometry": {"coordinates":[161.46494999999999,-9.5414],"type":"Point"}
}