{
  "type": "Feature",
  "properties": {
    "iso:country":"SB",
    "name:dan_x_preferred":[
        "Kokumbona"
    ],
    "name:eng_x_preferred":[
        "Kokumbona"
    ],
    "name:jpn_x_preferred":[
        "\u30b3\u30af\u30f3\u30dc\u30ca"
    ],
    "name:nld_x_preferred":[
        "Kokumbona"
    ],
    "name:zho_x_preferred":[
        "Kokumbuna\u6751"
    ],
    "qs:gn_pop":0,
    "qs:name":"Kakambona",
    "qs:name_adm0":"Solomon Islands",
    "qs:name_adm1":"Guadalcanal",
    "qs:photos":270,
    "qs:photos_1k":55,
    "qs:photos_9k":1,
    "qs:photos_9r":4,
    "qs:photos_all":270,
    "qs:photos_sr":5,
    "qs:placetype":"Town",
    "qs:pop_sr":"0",
    "qs:woe_adm0":23424766,
    "wd:wordcount":66,
    "wof:name":"Kakambona",
    "wof:placetype":"locality"
},
  "geometry": {"coordinates":[159.896736,-9.430265],"type":"Point"}
}