{
  "type": "Feature",
  "properties": {
    "gn:admin1_code":"0.0",
    "gn:asciiname":"Nonea",
    "gn:country_code":"SB",
    "gn:dem":21,
    "gn:feature_class":"P",
    "gn:feature_code":"PPL",
    "gn:name":"Nonea",
    "gn:population":0,
    "gn:timezone":"Pacific/Guadalcanal",
    "iso:country":"SB",
    "wof:name":"Nonea",
    "wof:placetype":"locality"
},
  "geometry": {"coordinates":[165.86463999999995,-10.86235],"type":"Point"}
}