{
  "type": "Feature",
  "properties": {
    "gn:admin1_code":"0.0",
    "gn:asciiname":"Nonea",
    "gn:country_code":"SB",
    "gn:dem":21,
    "gn:feature_class":"P",
    "gn:feature_code":"PPL",
    "gn:name":"Nonea",
    "gn:population":0,
    "gn:timezone":"Pacific/Guadalcanal",
    "iso:country":"SB",
    "name:bel_x_preferred":[
        "\u041d\u0430\u043d\u0435\u044f"
    ],
    "name:ceb_x_preferred":[
        "Nonea"
    ],
    "name:fas_x_preferred":[
        "\u0686\u0634\u0645\u200c\u06af\u0631\u0628\u0647\u200c\u0627\u06cc"
    ],
    "name:fin_x_preferred":[
        "Nunnat"
    ],
    "name:fra_x_preferred":[
        "Nonea"
    ],
    "name:hun_x_preferred":[
        "Ap\u00e1cavir\u00e1g"
    ],
    "name:ita_x_preferred":[
        "Nonea"
    ],
    "name:nld_x_preferred":[
        "Nonea"
    ],
    "name:pol_x_preferred":[
        "Zap\u0142onka"
    ],
    "name:por_x_preferred":[
        "Nonea"
    ],
    "name:rus_x_preferred":[
        "\u041d\u043e\u043d\u0435\u044f"
    ],
    "name:spa_x_preferred":[
        "Nonea"
    ],
    "name:swe_x_preferred":[
        "Nonneor"
    ],
    "name:ukr_x_preferred":[
        "\u041d\u043e\u043d\u0435\u044f"
    ],
    "name:war_x_preferred":[
        "Nonea"
    ],
    "name:zho_x_preferred":[
        "\u5047\u72fc\u7d2b\u8349\u5c5e"
    ],
    "wof:name":"Nonea",
    "wof:placetype":"locality"
},
  "geometry": {"coordinates":[165.86463999999995,-10.86235],"type":"Point"}
}