{
  "type": "Feature",
  "properties": {
    "gn:admin1_code":"0.0",
    "gn:asciiname":"Kwainangali",
    "gn:cc2":"SB",
    "gn:country_code":"SB",
    "gn:dem":501,
    "gn:feature_class":"P",
    "gn:feature_code":"PPL",
    "gn:name":"Kwainangali",
    "gn:population":0,
    "gn:timezone":"Pacific/Guadalcanal",
    "iso:country":"SB",
    "name:und_x_variant":[
        "Gwa\u2019ininiu",
        "Kwainangali"
    ],
    "wof:name":"Kwainangali",
    "wof:placetype":"locality"
},
  "geometry": {"coordinates":[160.81666999999999,-8.63333],"type":"Point"}
}