{
  "type": "Feature",
  "properties": {
    "gn:admin1_code":"0.0",
    "gn:asciiname":"Kolenamoa",
    "gn:country_code":"SB",
    "gn:dem":44,
    "gn:feature_class":"P",
    "gn:feature_code":"PPL",
    "gn:name":"Kolenamoa",
    "gn:population":0,
    "gn:timezone":"Pacific/Guadalcanal",
    "iso:country":"SB",
    "wof:name":"Kolenamoa",
    "wof:placetype":"locality"
},
  "geometry": {"coordinates":[156.71666999999999,-6.96667],"type":"Point"}
}