{
  "type": "Feature",
  "properties": {
    "gn:admin1_code":"0.0",
    "gn:asciiname":"Numbu",
    "gn:country_code":"SB",
    "gn:dem":25,
    "gn:feature_class":"P",
    "gn:feature_code":"PPL",
    "gn:name":"Numbu",
    "gn:population":0,
    "gn:timezone":"Pacific/Guadalcanal",
    "iso:country":"SB",
    "wof:name":"Numbu",
    "wof:placetype":"locality"
},
  "geometry": {"coordinates":[160.33941999999999,-9.50971],"type":"Point"}
}