{
  "type": "Feature",
  "properties": {
    "gn:admin1_code":"0.0",
    "gn:asciiname":"Kilusakwalo",
    "gn:country_code":"SB",
    "gn:dem":74,
    "gn:feature_class":"P",
    "gn:feature_code":"PPL",
    "gn:name":"Kilusakwalo",
    "gn:population":0,
    "gn:timezone":"Pacific/Guadalcanal",
    "iso:country":"SB",
    "wof:name":"Kilusakwalo",
    "wof:placetype":"locality"
},
  "geometry": {"coordinates":[160.70685,-8.74118],"type":"Point"}
}