{
  "type": "Feature",
  "properties": {
    "gn:admin1_code":"13.0",
    "gn:asciiname":"Ahanga",
    "gn:country_code":"SB",
    "gn:dem":32,
    "gn:feature_class":"P",
    "gn:feature_code":"PPL",
    "gn:name":"Ahanga",
    "gn:population":0,
    "gn:timezone":"Pacific/Guadalcanal",
    "iso:country":"SB",
    "wof:name":"Ahanga",
    "wof:placetype":"locality"
},
  "geometry": {"coordinates":[160.65593999999999,-11.83381],"type":"Point"}
}