{
  "type": "Feature",
  "properties": {
    "gn:admin1_code":"0.0",
    "gn:asciiname":"Mania",
    "gn:country_code":"SB",
    "gn:dem":13,
    "gn:feature_class":"P",
    "gn:feature_code":"PPL",
    "gn:name":"Mania",
    "gn:population":0,
    "gn:timezone":"Pacific/Guadalcanal",
    "iso:country":"SB",
    "wof:name":"Mania",
    "wof:placetype":"locality"
},
  "geometry": {"coordinates":[156.00236999999996,-7.01596],"type":"Point"}
}