{
  "type": "Feature",
  "properties": {
    "gn:admin1_code":"0.0",
    "gn:asciiname":"Manivasa",
    "gn:country_code":"SB",
    "gn:dem":14,
    "gn:feature_class":"P",
    "gn:feature_code":"PPL",
    "gn:name":"Manivasa",
    "gn:population":0,
    "gn:timezone":"Pacific/Guadalcanal",
    "iso:country":"SB",
    "wof:name":"Manivasa",
    "wof:placetype":"locality"
},
  "geometry": {"coordinates":[160.18666000000005,-9.81509],"type":"Point"}
}