{
  "type": "Feature",
  "properties": {
    "gn:admin1_code":"0.0",
    "gn:asciiname":"Kokomu",
    "gn:country_code":"SB",
    "gn:dem":5,
    "gn:feature_class":"P",
    "gn:feature_code":"PPL",
    "gn:name":"Kokomu",
    "gn:population":0,
    "gn:timezone":"Pacific/Guadalcanal",
    "iso:country":"SB",
    "name:und_x_variant":[
        "Kalibato",
        "Kokomu"
    ],
    "wof:name":"Kokomu",
    "wof:placetype":"locality"
},
  "geometry": {"coordinates":[160.15936000000005,-9.81621],"type":"Point"}
}