{
  "type": "Feature",
  "properties": {
    "gn:admin1_code":"0.0",
    "gn:asciiname":"Ndala",
    "gn:country_code":"SB",
    "gn:dem":18,
    "gn:feature_class":"P",
    "gn:feature_code":"PPL",
    "gn:name":"Ndala",
    "gn:population":0,
    "gn:timezone":"Pacific/Guadalcanal",
    "iso:country":"SB",
    "name:und_x_variant":[
        "Dala",
        "Ndala"
    ],
    "wof:name":"Ndala",
    "wof:placetype":"locality"
},
  "geometry": {"coordinates":[160.09259,-9.03723],"type":"Point"}
}