{
  "type": "Feature",
  "properties": {
    "gn:admin1_code":"0.0",
    "gn:asciiname":"Checheche",
    "gn:country_code":"SB",
    "gn:dem":85,
    "gn:feature_class":"P",
    "gn:feature_code":"PPL",
    "gn:name":"Checheche",
    "gn:population":0,
    "gn:timezone":"Pacific/Guadalcanal",
    "iso:country":"SB",
    "wof:name":"Checheche",
    "wof:placetype":"locality"
},
  "geometry": {"coordinates":[160.37554,-9.81626],"type":"Point"}
}