{
  "type": "Feature",
  "properties": {
    "gn:admin1_code":"0.0",
    "gn:asciiname":"Mbetilonga",
    "gn:country_code":"SB",
    "gn:dem":544,
    "gn:feature_class":"P",
    "gn:feature_code":"PPL",
    "gn:name":"Mbetilonga",
    "gn:population":0,
    "gn:timezone":"Pacific/Guadalcanal",
    "iso:country":"SB",
    "wof:name":"Mbetilonga",
    "wof:placetype":"locality"
},
  "geometry": {"coordinates":[159.97655,-9.5575],"type":"Point"}
}