{
  "type": "Feature",
  "properties": {
    "gn:admin1_code":"0.0",
    "gn:asciiname":"Veralevugha",
    "gn:country_code":"SB",
    "gn:dem":10,
    "gn:feature_class":"P",
    "gn:feature_code":"PPL",
    "gn:name":"Veralevugha",
    "gn:population":0,
    "gn:timezone":"Pacific/Guadalcanal",
    "iso:country":"SB",
    "wof:name":"Veralevugha",
    "wof:placetype":"locality"
},
  "geometry": {"coordinates":[159.59998999999999,-9.39435],"type":"Point"}
}