{
  "type": "Feature",
  "properties": {
    "gn:admin1_code":"0.0",
    "gn:asciiname":"Kmagha",
    "gn:country_code":"SB",
    "gn:dem":12,
    "gn:feature_class":"P",
    "gn:feature_code":"PPL",
    "gn:name":"Kmagha",
    "gn:population":0,
    "gn:timezone":"Pacific/Guadalcanal",
    "iso:country":"SB",
    "name:und_x_variant":[
        "Kimaga",
        "Kmagha"
    ],
    "wof:name":"Kmagha",
    "wof:placetype":"locality"
},
  "geometry": {"coordinates":[159.68738000000005,-8.21734],"type":"Point"}
}