{
  "type": "Feature",
  "properties": {
    "iso:country":"SB",
    "qs:gn_country":"SB",
    "qs:gn_fcode":"PPLX",
    "qs:gn_pop":0,
    "qs:name":"Mbumburu",
    "qs:name_adm0":"Solomon Islands",
    "qs:name_adm1":"Guadalcanal",
    "qs:photos":4,
    "qs:photos_1k":1,
    "qs:photos_9k":1,
    "qs:photos_9r":1,
    "qs:photos_all":4,
    "qs:photos_sr":1,
    "qs:placetype":"Suburb",
    "qs:pop_sr":"0",
    "qs:woe_adm0":23424766,
    "wd:wordcount":57,
    "wof:name":"Mbumburu",
    "wof:placetype":"neighbourhood"
},
  "geometry": {"coordinates":[159.93333000000001,-9.43333],"type":"Point"}
}