{
  "type": "Feature",
  "properties": {
    "gn:admin1_code":"0.0",
    "gn:asciiname":"Hangataru",
    "gn:country_code":"SB",
    "gn:dem":7,
    "gn:feature_class":"P",
    "gn:feature_code":"PPL",
    "gn:name":"Hangataru",
    "gn:population":0,
    "gn:timezone":"Pacific/Guadalcanal",
    "iso:country":"SB",
    "wof:name":"Hangataru",
    "wof:placetype":"locality"
},
  "geometry": {"coordinates":[161.31666999999999,-10.18333],"type":"Point"}
}