{
  "type": "Feature",
  "properties": {
    "gn:admin1_code":"0.0",
    "gn:asciiname":"Kofi",
    "gn:country_code":"SB",
    "gn:dem":10,
    "gn:feature_class":"P",
    "gn:feature_code":"PPL",
    "gn:name":"Kofi",
    "gn:population":0,
    "gn:timezone":"Pacific/Guadalcanal",
    "iso:country":"SB",
    "name:deu_x_preferred":[
        "Kofi"
    ],
    "name:fra_x_preferred":[
        "Koffi"
    ],
    "name:ita_x_preferred":[
        "Kofi"
    ],
    "name:nld_x_preferred":[
        "Kofi"
    ],
    "name:nor_x_preferred":[
        "Kofi"
    ],
    "wof:name":"Kofi",
    "wof:placetype":"locality"
},
  "geometry": {"coordinates":[157.33882,-8.60601],"type":"Point"}
}