{
  "type": "Feature",
  "properties": {
    "gn:admin1_code":"0.0",
    "gn:asciiname":"Ghombua",
    "gn:country_code":"SB",
    "gn:dem":17,
    "gn:feature_class":"P",
    "gn:feature_code":"PPL",
    "gn:name":"Ghombua",
    "gn:population":0,
    "gn:timezone":"Pacific/Guadalcanal",
    "iso:country":"SB",
    "name:und_x_variant":[
        "Gembua",
        "Gombua",
        "Ghombua"
    ],
    "wof:name":"Ghombua",
    "wof:placetype":"locality"
},
  "geometry": {"coordinates":[160.43446,-9.51943],"type":"Point"}
}