{
  "type": "Feature",
  "properties": {
    "gn:admin1_code":"0.0",
    "gn:asciiname":"Nonoropo",
    "gn:country_code":"SB",
    "gn:dem":28,
    "gn:feature_class":"P",
    "gn:feature_code":"PPL",
    "gn:name":"Nonoropo",
    "gn:population":0,
    "gn:timezone":"Pacific/Guadalcanal",
    "iso:country":"SB",
    "wof:name":"Nonoropo",
    "wof:placetype":"locality"
},
  "geometry": {"coordinates":[157.10718,-6.98412],"type":"Point"}
}