{
  "type": "Feature",
  "properties": {
    "gn:admin1_code":"0.0",
    "gn:asciiname":"Wawarioke",
    "gn:country_code":"SB",
    "gn:dem":7,
    "gn:feature_class":"P",
    "gn:feature_code":"PPL",
    "gn:name":"Wawarioke",
    "gn:population":0,
    "gn:timezone":"Pacific/Guadalcanal",
    "iso:country":"SB",
    "wof:name":"Wawarioke",
    "wof:placetype":"locality"
},
  "geometry": {"coordinates":[161.12405000000001,-9.34454],"type":"Point"}
}