{
  "type": "Feature",
  "properties": {
    "gn:admin1_code":"0.0",
    "gn:asciiname":"Onitewa",
    "gn:country_code":"SB",
    "gn:dem":12,
    "gn:feature_class":"P",
    "gn:feature_code":"PPL",
    "gn:name":"Onitewa",
    "gn:population":0,
    "gn:timezone":"Pacific/Guadalcanal",
    "iso:country":"SB",
    "name:und_x_variant":[
        "Untava",
        "Oneteva",
        "Onitewa"
    ],
    "wof:name":"Onitewa",
    "wof:placetype":"locality"
},
  "geometry": {"coordinates":[160.81587999999999,-9.87009],"type":"Point"}
}