{
  "type": "Feature",
  "properties": {
    "gn:admin1_code":"0.0",
    "gn:asciiname":"Faibubulia",
    "gn:country_code":"SB",
    "gn:dem":79,
    "gn:feature_class":"P",
    "gn:feature_code":"PPL",
    "gn:name":"Faibubulia",
    "gn:population":0,
    "gn:timezone":"Pacific/Guadalcanal",
    "iso:country":"SB",
    "wof:name":"Faibubulia",
    "wof:placetype":"locality"
},
  "geometry": {"coordinates":[160.69808999999995,-8.75405],"type":"Point"}
}