{
  "type": "Feature",
  "properties": {
    "gn:admin1_code":"0.0",
    "gn:asciiname":"Mamalade",
    "gn:country_code":"SB",
    "gn:dem":473,
    "gn:feature_class":"P",
    "gn:feature_code":"PPL",
    "gn:name":"Mamalade",
    "gn:population":0,
    "gn:timezone":"Pacific/Guadalcanal",
    "iso:country":"SB",
    "wof:name":"Mamalade",
    "wof:placetype":"locality"
},
  "geometry": {"coordinates":[160.77902,-8.80627],"type":"Point"}
}