{
  "type": "Feature",
  "properties": {
    "gn:admin1_code":"0.0",
    "gn:asciiname":"Vatunakuvukuvu",
    "gn:country_code":"SB",
    "gn:dem":1232,
    "gn:feature_class":"P",
    "gn:feature_code":"PPL",
    "gn:name":"Vatunakuvukuvu",
    "gn:population":0,
    "gn:timezone":"Pacific/Guadalcanal",
    "iso:country":"SB",
    "wof:name":"Vatunakuvukuvu",
    "wof:placetype":"locality"
},
  "geometry": {"coordinates":[160.60024000000001,-9.80863],"type":"Point"}
}