{
  "type": "Feature",
  "properties": {
    "gn:admin1_code":"0.0",
    "gn:asciiname":"Paa",
    "gn:country_code":"SB",
    "gn:dem":16,
    "gn:feature_class":"P",
    "gn:feature_code":"PPL",
    "gn:name":"Paa",
    "gn:population":0,
    "gn:timezone":"Pacific/Guadalcanal",
    "iso:country":"SB",
    "name:ceb_x_preferred":[
        "Paa"
    ],
    "name:swe_x_preferred":[
        "Paa"
    ],
    "wof:name":"Paa",
    "wof:placetype":"locality"
},
  "geometry": {"coordinates":[162.09703999999999,-10.49362],"type":"Point"}
}