{
  "type": "Feature",
  "properties": {
    "iso:country":"SB",
    "name:eng_x_preferred":[
        "Tavioa"
    ],
    "qs:gn_adm0_cc":"SB",
    "qs:gn_fcode":"PPLX",
    "qs:gn_local":2108502,
    "qs:gn_namadm1":"00",
    "qs:gn_name":"Tavioa",
    "qs:local_max":316,
    "qs:local_sum":370,
    "qs:localhoods":2,
    "qs:name":"Tavioa",
    "qs:name_adm0":"Solomon Islands",
    "qs:name_adm1":"Guadalcanal",
    "qs:name_local":"Honiara",
    "qs:photo_max":25,
    "qs:photo_sum":54,
    "qs:placetype":"Suburb",
    "qs:quad_count":7,
    "qs:woe_adm0":23424766,
    "qs:woe_adm1":2344839,
    "qs:woe_adm2":0,
    "qs:woe_lau":0,
    "qs:woe_local":1020496,
    "qs:woe_ver":"7.10.0",
    "wof:lang":[
        "eng"
    ],
    "wof:name":"Tavioa",
    "wof:placetype":"neighbourhood"
},
  "geometry": {"coordinates":[159.941709,-9.425078],"type":"Point"}
}