{
  "type": "Feature",
  "properties": {
    "gn:admin1_code":"0.0",
    "gn:asciiname":"Manewiriwiri",
    "gn:country_code":"SB",
    "gn:dem":12,
    "gn:feature_class":"P",
    "gn:feature_code":"PPL",
    "gn:name":"Manewiriwiri",
    "gn:population":0,
    "gn:timezone":"Pacific/Guadalcanal",
    "iso:country":"SB",
    "wof:name":"Manewiriwiri",
    "wof:placetype":"locality"
},
  "geometry": {"coordinates":[161.99251999999996,-10.49842],"type":"Point"}
}