{
  "type": "Feature",
  "properties": {
    "gn:admin1_code":"0.0",
    "gn:asciiname":"Marokafo",
    "gn:country_code":"SB",
    "gn:dem":69,
    "gn:feature_class":"P",
    "gn:feature_code":"PPL",
    "gn:name":"Marokafo",
    "gn:population":0,
    "gn:timezone":"Pacific/Guadalcanal",
    "iso:country":"SB",
    "wof:name":"Marokafo",
    "wof:placetype":"locality"
},
  "geometry": {"coordinates":[160.72253000000001,-8.40766],"type":"Point"}
}