{
  "type": "Feature",
  "properties": {
    "gn:admin1_code":"0.0",
    "gn:asciiname":"Werobungia",
    "gn:country_code":"SB",
    "gn:dem":213,
    "gn:feature_class":"P",
    "gn:feature_code":"PPL",
    "gn:name":"Werobungia",
    "gn:population":0,
    "gn:timezone":"Pacific/Guadalcanal",
    "iso:country":"SB",
    "name:und_x_variant":[
        "Verabuni",
        "Werobungia"
    ],
    "wof:name":"Werobungia",
    "wof:placetype":"locality"
},
  "geometry": {"coordinates":[162.05411999999995,-10.48308],"type":"Point"}
}