{
  "type": "Feature",
  "properties": {
    "gn:admin1_code":"0.0",
    "gn:asciiname":"Sautafi",
    "gn:country_code":"SB",
    "gn:dem":31,
    "gn:feature_class":"P",
    "gn:feature_code":"PPL",
    "gn:name":"Sautafi",
    "gn:population":0,
    "gn:timezone":"Pacific/Guadalcanal",
    "iso:country":"SB",
    "wof:name":"Sautafi",
    "wof:placetype":"locality"
},
  "geometry": {"coordinates":[168.82011,-12.30198],"type":"Point"}
}