{
  "type": "Feature",
  "properties": {
    "gn:admin1_code":"0.0",
    "gn:asciiname":"Na Naro",
    "gn:country_code":"SB",
    "gn:dem":316,
    "gn:feature_class":"P",
    "gn:feature_code":"PPL",
    "gn:name":"Na Naro",
    "gn:population":0,
    "gn:timezone":"Pacific/Guadalcanal",
    "iso:country":"SB",
    "wof:name":"Na Naro",
    "wof:placetype":"locality"
},
  "geometry": {"coordinates":[160.29024999999999,-9.60884],"type":"Point"}
}