{
  "type": "Feature",
  "properties": {
    "gn:admin1_code":"0.0",
    "gn:asciiname":"Pukambuti",
    "gn:country_code":"SB",
    "gn:dem":609,
    "gn:feature_class":"P",
    "gn:feature_code":"PPL",
    "gn:name":"Pukambuti",
    "gn:population":0,
    "gn:timezone":"Pacific/Guadalcanal",
    "iso:country":"SB",
    "wof:name":"Pukambuti",
    "wof:placetype":"locality"
},
  "geometry": {"coordinates":[160.22649999999999,-9.67932],"type":"Point"}
}