{
  "type": "Feature",
  "properties": {
    "gn:admin1_code":"0.0",
    "gn:asciiname":"Wairadina",
    "gn:country_code":"SB",
    "gn:dem":0,
    "gn:feature_class":"P",
    "gn:feature_code":"PPL",
    "gn:name":"Wairadina",
    "gn:population":0,
    "gn:timezone":"Pacific/Guadalcanal",
    "iso:country":"SB",
    "wof:name":"Wairadina",
    "wof:placetype":"locality"
},
  "geometry": {"coordinates":[161.18333000000001,-9.03333],"type":"Point"}
}