{
  "type": "Feature",
  "properties": {
    "gn:admin1_code":"0.0",
    "gn:asciiname":"Ungalesi",
    "gn:country_code":"SB",
    "gn:dem":17,
    "gn:feature_class":"P",
    "gn:feature_code":"PPL",
    "gn:name":"Ungalesi",
    "gn:population":0,
    "gn:timezone":"Pacific/Guadalcanal",
    "iso:country":"SB",
    "wof:name":"Ungalesi",
    "wof:placetype":"locality"
},
  "geometry": {"coordinates":[160.38215,-9.46664],"type":"Point"}
}