{
  "type": "Feature",
  "properties": {
    "gn:admin1_code":"0.0",
    "gn:asciiname":"Hihiaka Patukae",
    "gn:cc2":"SB",
    "gn:country_code":"SB",
    "gn:dem":-9999,
    "gn:feature_class":"P",
    "gn:feature_code":"PPL",
    "gn:name":"Hihiaka Patukae",
    "gn:population":0,
    "gn:timezone":"Pacific/Guadalcanal",
    "iso:country":"SB",
    "name:und_x_variant":[
        "Patukae",
        "Hihiaka",
        "Hihiaka Patukae"
    ],
    "wof:name":"Hihiaka Patukae",
    "wof:placetype":"locality"
},
  "geometry": {"coordinates":[158.03333000000001,-8.53333],"type":"Point"}
}