{
  "type": "Feature",
  "properties": {
    "gn:admin1_code":"0.0",
    "gn:asciiname":"Sungina",
    "gn:country_code":"SB",
    "gn:dem":105,
    "gn:feature_class":"P",
    "gn:feature_code":"PPL",
    "gn:name":"Sungina",
    "gn:population":0,
    "gn:timezone":"Pacific/Guadalcanal",
    "iso:country":"SB",
    "wof:name":"Sungina",
    "wof:placetype":"locality"
},
  "geometry": {"coordinates":[160.05577,-9.5057],"type":"Point"}
}