{
  "type": "Feature",
  "properties": {
    "gn:admin1_code":"0.0",
    "gn:asciiname":"Simba",
    "gn:country_code":"SB",
    "gn:dem":11,
    "gn:feature_class":"P",
    "gn:feature_code":"PPL",
    "gn:name":"Simba",
    "gn:population":0,
    "gn:timezone":"Pacific/Guadalcanal",
    "iso:country":"SB",
    "name:afr_x_preferred":[
        "Simba"
    ],
    "name:ara_x_preferred":[
        "\u0633\u0645\u0628\u0627"
    ],
    "name:ces_x_preferred":[
        "Simba"
    ],
    "name:fas_x_preferred":[
        "\u0633\u06cc\u0645\u0628\u0627"
    ],
    "name:fin_x_preferred":[
        "Simba"
    ],
    "name:fra_x_preferred":[
        "Simba"
    ],
    "name:guj_x_preferred":[
        "\u0ab8\u0abf\u0aae\u0acd\u0aac\u0abe"
    ],
    "name:heb_x_preferred":[
        "\u05e1\u05d9\u05de\u05d1\u05d4"
    ],
    "name:ind_x_preferred":[
        "Simba"
    ],
    "name:ita_x_preferred":[
        "Simba"
    ],
    "name:mal_x_preferred":[
        "\u0d38\u0d3f\u0d02\u0d2c"
    ],
    "name:nld_x_preferred":[
        "Simba"
    ],
    "name:nor_x_preferred":[
        "Simba"
    ],
    "name:pan_x_preferred":[
        "\u0a38\u0a3f\u0a2e\u0a2c\u0a3e"
    ],
    "name:pnb_x_preferred":[
        "\u0633\u0650\u0645\u0628\u0627"
    ],
    "name:por_x_preferred":[
        "Simba"
    ],
    "name:rus_x_preferred":[
        "\u0421\u0438\u043c\u0431\u0430"
    ],
    "name:spa_x_preferred":[
        "Simba"
    ],
    "name:srp_x_preferred":[
        "\u0421\u0438\u043c\u0431\u0430"
    ],
    "name:tam_x_preferred":[
        "\u0b9a\u0bbf\u0bae\u0bcd\u0baa\u0bbe"
    ],
    "name:ukr_x_preferred":[
        "\u0421\u0456\u043c\u0431\u0430"
    ],
    "name:urd_x_preferred":[
        "\u0633\u0645\u0628\u0627"
    ],
    "wof:name":"Simba",
    "wof:placetype":"locality"
},
  "geometry": {"coordinates":[160.31115,-9.4256],"type":"Point"}
}