{
  "type": "Feature",
  "properties": {
    "gn:admin1_code":"0.0",
    "gn:asciiname":"Firifau",
    "gn:country_code":"SB",
    "gn:dem":4,
    "gn:feature_class":"P",
    "gn:feature_code":"PPL",
    "gn:name":"Firifau",
    "gn:population":0,
    "gn:timezone":"Pacific/Guadalcanal",
    "iso:country":"SB",
    "wof:name":"Firifau",
    "wof:placetype":"locality"
},
  "geometry": {"coordinates":[160.74271999999999,-8.8608],"type":"Point"}
}