{
  "type": "Feature",
  "properties": {
    "gn:admin1_code":"0.0",
    "gn:asciiname":"Sagheraghi",
    "gn:country_code":"SB",
    "gn:dem":11,
    "gn:feature_class":"P",
    "gn:feature_code":"PPL",
    "gn:name":"Sagheraghi",
    "gn:population":0,
    "gn:timezone":"Pacific/Guadalcanal",
    "iso:country":"SB",
    "wof:name":"Sagheraghi",
    "wof:placetype":"locality"
},
  "geometry": {"coordinates":[156.77615,-8.043],"type":"Point"}
}