{
  "type": "Feature",
  "properties": {
    "gn:admin1_code":"0.0",
    "gn:asciiname":"Ngalilalali",
    "gn:country_code":"SB",
    "gn:dem":19,
    "gn:feature_class":"P",
    "gn:feature_code":"PPL",
    "gn:name":"Ngalilalali",
    "gn:population":0,
    "gn:timezone":"Pacific/Guadalcanal",
    "iso:country":"SB",
    "wof:name":"Ngalilalali",
    "wof:placetype":"locality"
},
  "geometry": {"coordinates":[160.25,-9.45],"type":"Point"}
}