{
  "type": "Feature",
  "properties": {
    "gn:admin1_code":"0.0",
    "gn:asciiname":"Omirangia",
    "gn:country_code":"SB",
    "gn:dem":1,
    "gn:feature_class":"P",
    "gn:feature_code":"PPL",
    "gn:name":"Omirangia",
    "gn:population":0,
    "gn:timezone":"Pacific/Guadalcanal",
    "iso:country":"SB",
    "wof:name":"Omirangia",
    "wof:placetype":"locality"
},
  "geometry": {"coordinates":[160.43253999999999,-9.46613],"type":"Point"}
}