{
  "type": "Feature",
  "properties": {
    "gn:admin1_code":"0.0",
    "gn:asciiname":"Ngaringari",
    "gn:country_code":"SB",
    "gn:dem":105,
    "gn:feature_class":"P",
    "gn:feature_code":"PPL",
    "gn:name":"Ngaringari",
    "gn:population":0,
    "gn:timezone":"Pacific/Guadalcanal",
    "iso:country":"SB",
    "wof:name":"Ngaringari",
    "wof:placetype":"locality"
},
  "geometry": {"coordinates":[156.56666999999999,-6.85],"type":"Point"}
}