{
  "type": "Feature",
  "properties": {
    "gn:admin1_code":"0.0",
    "gn:asciiname":"Maraeva",
    "gn:country_code":"SB",
    "gn:dem":14,
    "gn:feature_class":"P",
    "gn:feature_code":"PPL",
    "gn:name":"Maraeva",
    "gn:population":0,
    "gn:timezone":"Pacific/Guadalcanal",
    "iso:country":"SB",
    "name:und_x_variant":[
        "Mariava",
        "Maraiva",
        "Maraeva"
    ],
    "wof:name":"Maraeva",
    "wof:placetype":"locality"
},
  "geometry": {"coordinates":[160.58529999999999,-9.92011],"type":"Point"}
}