{
  "type": "Feature",
  "properties": {
    "gn:admin1_code":"0.0",
    "gn:asciiname":"Narohei",
    "gn:country_code":"SB",
    "gn:dem":41,
    "gn:feature_class":"P",
    "gn:feature_code":"PPL",
    "gn:name":"Narohei",
    "gn:population":0,
    "gn:timezone":"Pacific/Guadalcanal",
    "iso:country":"SB",
    "wof:name":"Narohei",
    "wof:placetype":"locality"
},
  "geometry": {"coordinates":[161.83333000000005,-10.75],"type":"Point"}
}