{
  "type": "Feature",
  "properties": {
    "gn:admin1_code":"0.0",
    "gn:asciiname":"Marararo",
    "gn:country_code":"SB",
    "gn:dem":284,
    "gn:feature_class":"P",
    "gn:feature_code":"PPL",
    "gn:name":"Marararo",
    "gn:population":0,
    "gn:timezone":"Pacific/Guadalcanal",
    "iso:country":"SB",
    "wof:name":"Marararo",
    "wof:placetype":"locality"
},
  "geometry": {"coordinates":[161.05000000000001,-9.25],"type":"Point"}
}