{
  "type": "Feature",
  "properties": {
    "iso:country":"SB",
    "name:ast_x_preferred":[
        "Kirakira"
    ],
    "name:bul_x_preferred":[
        "\u041a\u0438\u0440\u0430\u043a\u0438\u0440\u0430"
    ],
    "name:ceb_x_preferred":[
        "Kirakira"
    ],
    "name:ces_x_preferred":[
        "Kirakira"
    ],
    "name:deu_x_preferred":[
        "Kirakira"
    ],
    "name:eng_x_preferred":[
        "Kirakira"
    ],
    "name:fas_x_preferred":[
        "\u06a9\u06cc\u0631\u0627\u06a9\u06cc\u0631\u0627"
    ],
    "name:fra_x_preferred":[
        "Kirakira"
    ],
    "name:glg_x_preferred":[
        "Kirakira"
    ],
    "name:heb_x_preferred":[
        "\u05e7\u05d9\u05e8\u05d0\u05e7\u05d9\u05e8\u05d4"
    ],
    "name:hrv_x_preferred":[
        "Kirakira"
    ],
    "name:ita_x_preferred":[
        "Kirakira"
    ],
    "name:jpn_x_preferred":[
        "\u30ad\u30e9\u30ad\u30e9"
    ],
    "name:lit_x_preferred":[
        "Kirakira"
    ],
    "name:mrj_x_preferred":[
        "\u041a\u0438\u0440\u0430\u043a\u0438\u0440\u0430"
    ],
    "name:nau_x_preferred":[
        "Kirakira"
    ],
    "name:nld_x_preferred":[
        "Kirakira"
    ],
    "name:pol_x_preferred":[
        "Kirakira"
    ],
    "name:por_x_preferred":[
        "Kirakira"
    ],
    "name:rus_x_preferred":[
        "\u041a\u0438\u0440\u0430\u043a\u0438\u0440\u0430"
    ],
    "name:spa_x_preferred":[
        "Kirakira"
    ],
    "name:ukr_x_preferred":[
        "\u041a\u0456\u0440\u0430\u043a\u0456\u0440\u0430"
    ],
    "name:urd_x_preferred":[
        "\u06a9\u06cc\u0631\u0627\u06a9\u06cc\u0631\u0627"
    ],
    "name:vie_x_preferred":[
        "Kirakira"
    ],
    "name:zho_x_preferred":[
        "\u57fa\u62c9\u57fa\u62c9"
    ],
    "qs:gn_country":"SB",
    "qs:gn_fcode":"PPL",
    "qs:gn_pop":1122,
    "qs:name":"Kirakira",
    "qs:name_adm0":"Solomon Islands",
    "qs:name_adm1":"Makira",
    "qs:photos":0,
    "qs:photos_1k":0,
    "qs:photos_9k":0,
    "qs:photos_9r":0,
    "qs:photos_all":0,
    "qs:photos_sr":0,
    "qs:placetype":"Town",
    "qs:pop_sr":"3",
    "qs:woe_adm0":23424766,
    "wd:wordcount":2475,
    "wof:name":"Kirakira",
    "wof:placetype":"locality",
    "wof:population":1122
},
  "geometry": {"coordinates":[161.92044999999999,-10.45442],"type":"Point"}
}