{
  "type": "Feature",
  "properties": {
    "gn:admin1_code":"0.0",
    "gn:asciiname":"Wakora",
    "gn:country_code":"SB",
    "gn:dem":113,
    "gn:feature_class":"P",
    "gn:feature_code":"PPL",
    "gn:name":"Wakora",
    "gn:population":0,
    "gn:timezone":"Pacific/Guadalcanal",
    "iso:country":"SB",
    "wof:name":"Wakora",
    "wof:placetype":"locality"
},
  "geometry": {"coordinates":[161.84999999999999,-10.76667],"type":"Point"}
}