{
  "type": "Feature",
  "properties": {
    "gn:admin1_code":"0.0",
    "gn:asciiname":"Komuna",
    "gn:country_code":"SB",
    "gn:dem":594,
    "gn:feature_class":"P",
    "gn:feature_code":"PPL",
    "gn:name":"Komuna",
    "gn:population":0,
    "gn:timezone":"Pacific/Guadalcanal",
    "iso:country":"SB",
    "name:bul_x_preferred":[
        "\u041a\u043e\u043c\u0443\u043d\u0430"
    ],
    "name:ces_x_preferred":[
        "Komuna"
    ],
    "name:deu_x_preferred":[
        "Komuna"
    ],
    "name:pol_x_preferred":[
        "Komuna"
    ],
    "name:slk_x_preferred":[
        "Kom\u00fana"
    ],
    "name:ukr_x_preferred":[
        "\u041a\u043e\u043c\u0443\u043d\u0430"
    ],
    "wof:name":"Komuna",
    "wof:placetype":"locality"
},
  "geometry": {"coordinates":[160.57613000000001,-9.72096],"type":"Point"}
}