{
  "type": "Feature",
  "properties": {
    "gn:admin1_code":"0.0",
    "gn:asciiname":"Komuna",
    "gn:country_code":"SB",
    "gn:dem":594,
    "gn:feature_class":"P",
    "gn:feature_code":"PPL",
    "gn:name":"Komuna",
    "gn:population":0,
    "gn:timezone":"Pacific/Guadalcanal",
    "iso:country":"SB",
    "wof:name":"Komuna",
    "wof:placetype":"locality"
},
  "geometry": {"coordinates":[160.57613000000001,-9.72096],"type":"Point"}
}