{
  "type": "Feature",
  "properties": {
    "gn:admin1_code":"0.0",
    "gn:asciiname":"Njenjepele",
    "gn:cc2":"SB",
    "gn:country_code":"SB",
    "gn:dem":93,
    "gn:feature_class":"P",
    "gn:feature_code":"PPL",
    "gn:name":"Njenjepele",
    "gn:population":0,
    "gn:timezone":"Pacific/Guadalcanal",
    "iso:country":"SB",
    "name:und_x_variant":[
        "Jinjapili",
        "Njenjepele"
    ],
    "wof:name":"Njenjepele",
    "wof:placetype":"locality"
},
  "geometry": {"coordinates":[157.09999999999999,-6.98333],"type":"Point"}
}