{
  "type": "Feature",
  "properties": {
    "gn:admin1_code":"0.0",
    "gn:asciiname":"Mbumbumaraho",
    "gn:country_code":"SB",
    "gn:dem":420,
    "gn:feature_class":"P",
    "gn:feature_code":"PPL",
    "gn:name":"Mbumbumaraho",
    "gn:population":0,
    "gn:timezone":"Pacific/Guadalcanal",
    "iso:country":"SB",
    "wof:name":"Mbumbumaraho",
    "wof:placetype":"locality"
},
  "geometry": {"coordinates":[160.46152000000001,-9.63973],"type":"Point"}
}