{
  "type": "Feature",
  "properties": {
    "gn:admin1_code":"0.0",
    "gn:asciiname":"Raia",
    "gn:country_code":"SB",
    "gn:dem":192,
    "gn:feature_class":"P",
    "gn:feature_code":"PPL",
    "gn:name":"Raia",
    "gn:population":0,
    "gn:timezone":"Pacific/Guadalcanal",
    "iso:country":"SB",
    "wof:name":"Raia",
    "wof:placetype":"locality"
},
  "geometry": {"coordinates":[161.26667,-9.35],"type":"Point"}
}