{
  "type": "Feature",
  "properties": {
    "gn:admin1_code":"0.0",
    "gn:asciiname":"Tuhurutolu",
    "gn:country_code":"SB",
    "gn:dem":930,
    "gn:feature_class":"P",
    "gn:feature_code":"PPL",
    "gn:name":"Tuhurutolu",
    "gn:population":0,
    "gn:timezone":"Pacific/Guadalcanal",
    "iso:country":"SB",
    "wof:name":"Tuhurutolu",
    "wof:placetype":"locality"
},
  "geometry": {"coordinates":[160.05156000000005,-9.61516],"type":"Point"}
}