{
  "type": "Feature",
  "properties": {
    "gn:admin1_code":"0.0",
    "gn:asciiname":"Dedeu",
    "gn:country_code":"SB",
    "gn:dem":0,
    "gn:feature_class":"P",
    "gn:feature_code":"PPL",
    "gn:name":"Dedeu",
    "gn:population":0,
    "gn:timezone":"Pacific/Guadalcanal",
    "iso:country":"SB",
    "wof:name":"Dedeu",
    "wof:placetype":"locality"
},
  "geometry": {"coordinates":[158.86983999999995,-7.96393],"type":"Point"}
}