{
  "type": "Feature",
  "properties": {
    "gn:admin1_code":"0.0",
    "gn:asciiname":"Tasia",
    "gn:country_code":"SB",
    "gn:dem":25,
    "gn:feature_class":"P",
    "gn:feature_code":"PPL",
    "gn:name":"Tasia",
    "gn:population":0,
    "gn:timezone":"Pacific/Guadalcanal",
    "iso:country":"SB",
    "wof:name":"Tasia",
    "wof:placetype":"locality"
},
  "geometry": {"coordinates":[159.61265,-8.14015],"type":"Point"}
}