{
  "type": "Feature",
  "properties": {
    "gn:admin1_code":"0.0",
    "gn:asciiname":"Waima'aka",
    "gn:country_code":"SB",
    "gn:dem":10,
    "gn:feature_class":"P",
    "gn:feature_code":"PPL",
    "gn:name":"Waima\u2019aka",
    "gn:population":0,
    "gn:timezone":"Pacific/Guadalcanal",
    "iso:country":"SB",
    "name:und_x_variant":[
        "Moki",
        "Waima\u2019aka"
    ],
    "wof:name":"Waima'aka",
    "wof:placetype":"locality"
},
  "geometry": {"coordinates":[161.1816,-9.05577],"type":"Point"}
}