{
  "type": "Feature",
  "properties": {
    "gn:admin1_code":"0.0",
    "gn:asciiname":"Okwala",
    "gn:country_code":"SB",
    "gn:dem":360,
    "gn:feature_class":"P",
    "gn:feature_code":"PPL",
    "gn:name":"Okwala",
    "gn:population":0,
    "gn:timezone":"Pacific/Guadalcanal",
    "iso:country":"SB",
    "wof:name":"Okwala",
    "wof:placetype":"locality"
},
  "geometry": {"coordinates":[160.81683000000001,-8.69876],"type":"Point"}
}