{
  "type": "Feature",
  "properties": {
    "gn:admin1_code":"0.0",
    "gn:asciiname":"Galovae",
    "gn:country_code":"SB",
    "gn:dem":9,
    "gn:feature_class":"P",
    "gn:feature_code":"PPL",
    "gn:name":"Galovae",
    "gn:population":0,
    "gn:timezone":"Pacific/Guadalcanal",
    "iso:country":"SB",
    "wof:name":"Galovae",
    "wof:placetype":"locality"
},
  "geometry": {"coordinates":[156.99608000000001,-7.24213],"type":"Point"}
}