{
  "type": "Feature",
  "properties": {
    "gn:admin1_code":"0.0",
    "gn:asciiname":"Fanelei",
    "gn:country_code":"SB",
    "gn:dem":-9999,
    "gn:feature_class":"P",
    "gn:feature_code":"PPL",
    "gn:name":"Fanelei",
    "gn:population":0,
    "gn:timezone":"Pacific/Guadalcanal",
    "iso:country":"SB",
    "name:und_x_variant":[
        "Fanalei",
        "Fanelei"
    ],
    "wof:name":"Fanelei",
    "wof:placetype":"locality"
},
  "geometry": {"coordinates":[161.55116000000001,-9.55951],"type":"Point"}
}