{
  "type": "Feature",
  "properties": {
    "gn:admin1_code":"0.0",
    "gn:asciiname":"Gatakesa",
    "gn:country_code":"SB",
    "gn:dem":52,
    "gn:feature_class":"P",
    "gn:feature_code":"PPL",
    "gn:name":"Gatakesa",
    "gn:population":0,
    "gn:timezone":"Pacific/Guadalcanal",
    "iso:country":"SB",
    "wof:name":"Gatakesa",
    "wof:placetype":"locality"
},
  "geometry": {"coordinates":[156.76667,-7.01667],"type":"Point"}
}