{
  "type": "Feature",
  "properties": {
    "gn:admin1_code":"0.0",
    "gn:asciiname":"Monitawa",
    "gn:country_code":"SB",
    "gn:dem":30,
    "gn:feature_class":"P",
    "gn:feature_code":"PPL",
    "gn:name":"Monitawa",
    "gn:population":0,
    "gn:timezone":"Pacific/Guadalcanal",
    "iso:country":"SB",
    "wof:name":"Monitawa",
    "wof:placetype":"locality"
},
  "geometry": {"coordinates":[162.27251999999999,-10.73421],"type":"Point"}
}