{
  "type": "Feature",
  "properties": {
    "gn:admin1_code":"0.0",
    "gn:asciiname":"Fata'olo",
    "gn:country_code":"SB",
    "gn:dem":53,
    "gn:feature_class":"P",
    "gn:feature_code":"PPL",
    "gn:name":"Fata\u2019olo",
    "gn:population":0,
    "gn:timezone":"Pacific/Guadalcanal",
    "iso:country":"SB",
    "wof:name":"Fata'olo",
    "wof:placetype":"locality"
},
  "geometry": {"coordinates":[160.79022000000001,-8.39921],"type":"Point"}
}