{
  "type": "Feature",
  "properties": {
    "gn:admin1_code":"0.0",
    "gn:asciiname":"Nodana",
    "gn:country_code":"SB",
    "gn:dem":64,
    "gn:feature_class":"P",
    "gn:feature_code":"PPL",
    "gn:name":"Nodana",
    "gn:population":0,
    "gn:timezone":"Pacific/Guadalcanal",
    "iso:country":"SB",
    "wof:name":"Nodana",
    "wof:placetype":"locality"
},
  "geometry": {"coordinates":[159.75085000000001,-8.29084],"type":"Point"}
}