{
  "type": "Feature",
  "properties": {
    "gn:admin1_code":"0.0",
    "gn:asciiname":"Ocili",
    "gn:country_code":"SB",
    "gn:dem":86,
    "gn:feature_class":"P",
    "gn:feature_code":"PPL",
    "gn:name":"Ocili",
    "gn:population":0,
    "gn:timezone":"Pacific/Guadalcanal",
    "iso:country":"SB",
    "wof:name":"Ocili",
    "wof:placetype":"locality"
},
  "geometry": {"coordinates":[166.94999999999999,-11.68333],"type":"Point"}
}