{
  "type": "Feature",
  "properties": {
    "gn:admin1_code":"0.0",
    "gn:asciiname":"Lipe",
    "gn:country_code":"SB",
    "gn:dem":9,
    "gn:feature_class":"P",
    "gn:feature_code":"PPL",
    "gn:name":"Lipe",
    "gn:population":0,
    "gn:timezone":"Pacific/Guadalcanal",
    "iso:country":"SB",
    "name:bos_x_preferred":[
        "Lipe"
    ],
    "name:ceb_x_preferred":[
        "Lipe"
    ],
    "name:fra_x_preferred":[
        "Lipe"
    ],
    "name:slv_x_preferred":[
        "Lipe"
    ],
    "name:srp_x_preferred":[
        "\u041b\u0438\u043f\u0435"
    ],
    "name:swe_x_preferred":[
        "Lipe"
    ],
    "wof:name":"Lipe",
    "wof:placetype":"locality"
},
  "geometry": {"coordinates":[166.35803999999999,-10.26522],"type":"Point"}
}