{
  "type": "Feature",
  "properties": {
    "gn:admin1_code":"0.0",
    "gn:asciiname":"Ailau",
    "gn:country_code":"SB",
    "gn:dem":6,
    "gn:feature_class":"P",
    "gn:feature_code":"PPL",
    "gn:name":"Ailau",
    "gn:population":0,
    "gn:timezone":"Pacific/Guadalcanal",
    "iso:country":"SB",
    "wof:name":"Ailau",
    "wof:placetype":"locality"
},
  "geometry": {"coordinates":[160.76133000000004,-8.92374],"type":"Point"}
}