{
  "type": "Feature",
  "properties": {
    "gn:admin1_code":"0.0",
    "gn:asciiname":"Kolumbaghea",
    "gn:country_code":"SB",
    "gn:dem":13,
    "gn:feature_class":"P",
    "gn:feature_code":"PPL",
    "gn:name":"Kolumbaghea",
    "gn:population":0,
    "gn:timezone":"Pacific/Guadalcanal",
    "iso:country":"SB",
    "name:und_x_variant":[
        "Kokombagia",
        "Kolombagia",
        "Kolumbaghea",
        "Kolumbungara"
    ],
    "wof:name":"Kolumbaghea",
    "wof:placetype":"locality"
},
  "geometry": {"coordinates":[157.59687,-8.0227],"type":"Point"}
}