{
  "type": "Feature",
  "properties": {
    "gn:admin1_code":"0.0",
    "gn:asciiname":"Komunimbaimbai",
    "gn:country_code":"SB",
    "gn:dem":11,
    "gn:feature_class":"P",
    "gn:feature_code":"PPL",
    "gn:name":"Komunimbaimbai",
    "gn:population":0,
    "gn:timezone":"Pacific/Guadalcanal",
    "iso:country":"SB",
    "wof:name":"Komunimbaimbai",
    "wof:placetype":"locality"
},
  "geometry": {"coordinates":[160.82435000000001,-9.85809],"type":"Point"}
}