{
  "type": "Feature",
  "properties": {
    "gn:admin1_code":"0.0",
    "gn:asciiname":"Kafulafiu",
    "gn:country_code":"SB",
    "gn:dem":19,
    "gn:feature_class":"P",
    "gn:feature_code":"PPL",
    "gn:name":"Kafulafiu",
    "gn:population":0,
    "gn:timezone":"Pacific/Guadalcanal",
    "iso:country":"SB",
    "wof:name":"Kafulafiu",
    "wof:placetype":"locality"
},
  "geometry": {"coordinates":[160.90000000000001,-8.85],"type":"Point"}
}