{
  "type": "Feature",
  "properties": {
    "gn:admin1_code":"0.0",
    "gn:asciiname":"Nimaniaihura",
    "gn:country_code":"SB",
    "gn:dem":266,
    "gn:feature_class":"P",
    "gn:feature_code":"PPL",
    "gn:name":"Nimaniaihura",
    "gn:population":0,
    "gn:timezone":"Pacific/Guadalcanal",
    "iso:country":"SB",
    "name:und_x_variant":[
        "Poreniaro",
        "Nimaniaihura"
    ],
    "wof:name":"Nimaniaihura",
    "wof:placetype":"locality"
},
  "geometry": {"coordinates":[161.28516000000005,-9.39426],"type":"Point"}
}