{
  "type": "Feature",
  "properties": {
    "gn:admin1_code":"0.0",
    "gn:asciiname":"Tawaaro",
    "gn:country_code":"SB",
    "gn:dem":4,
    "gn:feature_class":"P",
    "gn:feature_code":"PPL",
    "gn:name":"Tawaaro",
    "gn:population":0,
    "gn:timezone":"Pacific/Guadalcanal",
    "iso:country":"SB",
    "wof:name":"Tawaaro",
    "wof:placetype":"locality"
},
  "geometry": {"coordinates":[161.51211999999995,-9.5177],"type":"Point"}
}