{
  "type": "Feature",
  "properties": {
    "gn:admin1_code":"0.0",
    "gn:asciiname":"'Aimela",
    "gn:country_code":"SB",
    "gn:dem":43,
    "gn:feature_class":"P",
    "gn:feature_code":"PPL",
    "gn:name":"\u2019Aimela",
    "gn:population":0,
    "gn:timezone":"Pacific/Guadalcanal",
    "iso:country":"SB",
    "wof:name":"'Aimela",
    "wof:placetype":"locality"
},
  "geometry": {"coordinates":[160.70349999999999,-8.73274],"type":"Point"}
}