{
  "type": "Feature",
  "properties": {
    "gn:admin1_code":"0.0",
    "gn:asciiname":"Vakambo",
    "gn:country_code":"SB",
    "gn:dem":7,
    "gn:feature_class":"P",
    "gn:feature_code":"PPL",
    "gn:name":"Vakambo",
    "gn:population":0,
    "gn:timezone":"Pacific/Guadalcanal",
    "iso:country":"SB",
    "name:und_x_variant":[
        "Makambo",
        "Vakambo"
    ],
    "wof:name":"Vakambo",
    "wof:placetype":"locality"
},
  "geometry": {"coordinates":[157.84727000000001,-8.3715],"type":"Point"}
}