{
  "type": "Feature",
  "properties": {
    "gn:admin1_code":"0.0",
    "gn:asciiname":"Down Wind",
    "gn:cc2":"SB",
    "gn:country_code":"SB",
    "gn:dem":36,
    "gn:feature_class":"P",
    "gn:feature_code":"PPL",
    "gn:name":"Down Wind",
    "gn:population":0,
    "gn:timezone":"Pacific/Guadalcanal",
    "iso:country":"SB",
    "name:und_x_variant":[
        "Kolokeleve",
        "Down Wind"
    ],
    "wof:name":"Down Wind",
    "wof:placetype":"locality"
},
  "geometry": {"coordinates":[159.75,-8.28333],"type":"Point"}
}