{
  "type": "Feature",
  "properties": {
    "gn:admin1_code":"0.0",
    "gn:asciiname":"Samaria",
    "gn:country_code":"SB",
    "gn:dem":497,
    "gn:feature_class":"P",
    "gn:feature_code":"PPL",
    "gn:name":"Samaria",
    "gn:population":0,
    "gn:timezone":"Pacific/Guadalcanal",
    "iso:country":"SB",
    "wof:name":"Samaria",
    "wof:placetype":"locality"
},
  "geometry": {"coordinates":[160.84999999999999,-8.51667],"type":"Point"}
}