{
  "type": "Feature",
  "properties": {
    "gn:admin1_code":"0.0",
    "gn:asciiname":"Samaria",
    "gn:country_code":"SB",
    "gn:dem":497,
    "gn:feature_class":"P",
    "gn:feature_code":"PPL",
    "gn:name":"Samaria",
    "gn:population":0,
    "gn:timezone":"Pacific/Guadalcanal",
    "iso:country":"SB",
    "name:als_x_preferred":[
        "Samarien"
    ],
    "name:ara_x_preferred":[
        "\u0627\u0644\u0633\u0627\u0645\u0631\u0629"
    ],
    "name:arc_x_preferred":[
        "\u0712\u071d\u072c \u072b\u0721\u072a\u071d\u0710"
    ],
    "name:bel_x_preferred":[
        "\u0421\u0430\u043c\u0430\u0440\u044b\u044f"
    ],
    "name:bul_x_preferred":[
        "\u0421\u0430\u043c\u0430\u0440\u0438\u044f"
    ],
    "name:cat_x_preferred":[
        "Samaria"
    ],
    "name:ces_x_preferred":[
        "Sama\u0159sko"
    ],
    "name:dan_x_preferred":[
        "Samaria"
    ],
    "name:deu_x_preferred":[
        "Samarien"
    ],
    "name:epo_x_preferred":[
        "Samario"
    ],
    "name:eus_x_preferred":[
        "Samaria"
    ],
    "name:fao_x_preferred":[
        "Sam\u00e1ria"
    ],
    "name:fas_x_preferred":[
        "\u0633\u0627\u0645\u0631\u06cc\u0647"
    ],
    "name:fra_x_preferred":[
        "Samarie"
    ],
    "name:gle_x_preferred":[
        "An tSam\u00e1ir"
    ],
    "name:heb_x_preferred":[
        "\u05d4\u05e9\u05d5\u05de\u05e8\u05d5\u05df"
    ],
    "name:hun_x_preferred":[
        "Szam\u00e1ria"
    ],
    "name:hye_x_preferred":[
        "\u054d\u0561\u0574\u0561\u0580\u056b\u0561"
    ],
    "name:ind_x_preferred":[
        "Samaria"
    ],
    "name:ita_x_preferred":[
        "Samaria"
    ],
    "name:jpn_x_preferred":[
        "\u30b5\u30de\u30ea\u30a2"
    ],
    "name:kor_x_preferred":[
        "\uc0ac\ub9c8\ub9ac\uc544"
    ],
    "name:lat_x_preferred":[
        "Samaria"
    ],
    "name:lit_x_preferred":[
        "Samarija"
    ],
    "name:mar_x_preferred":[
        "\u0938\u092e\u0947\u0930\u093f\u092f\u093e"
    ],
    "name:nld_x_preferred":[
        "Samaria"
    ],
    "name:nno_x_preferred":[
        "Samaria"
    ],
    "name:nor_x_preferred":[
        "Samaria"
    ],
    "name:oci_x_preferred":[
        "Sam\u00e0ria"
    ],
    "name:pol_x_preferred":[
        "Samaria"
    ],
    "name:por_x_preferred":[
        "Samaria"
    ],
    "name:ron_x_preferred":[
        "Samaria"
    ],
    "name:rus_x_preferred":[
        "\u0421\u0430\u043c\u0430\u0440\u0438\u044f"
    ],
    "name:slv_x_preferred":[
        "Samarija"
    ],
    "name:spa_x_preferred":[
        "Samaria"
    ],
    "name:srp_x_preferred":[
        "Samarija"
    ],
    "name:swa_x_preferred":[
        "Samaria"
    ],
    "name:swe_x_preferred":[
        "Samarien"
    ],
    "name:tam_x_preferred":[
        "\u0b9a\u0bae\u0bbe\u0bb0\u0bbf\u0baf\u0bbe"
    ],
    "name:tur_x_preferred":[
        "Samarya"
    ],
    "name:ukr_x_preferred":[
        "\u0421\u0430\u043c\u0430\u0440\u0456\u044f"
    ],
    "name:urd_x_preferred":[
        "\u0633\u0627\u0645\u0631\u06c1"
    ],
    "name:uzb_x_preferred":[
        "Samariya"
    ],
    "name:yid_x_preferred":[
        "\u05e9\u05d5\u05de\u05e8\u05d5\u05df"
    ],
    "name:zho_x_preferred":[
        "\u6492\u99ac\u5229\u4e9e"
    ],
    "wof:name":"Samaria",
    "wof:placetype":"locality"
},
  "geometry": {"coordinates":[160.84999999999999,-8.51667],"type":"Point"}
}