{
  "type": "Feature",
  "properties": {
    "gn:admin1_code":"0.0",
    "gn:asciiname":"Selavana",
    "gn:country_code":"SB",
    "gn:dem":44,
    "gn:feature_class":"P",
    "gn:feature_code":"PPL",
    "gn:name":"Selavana",
    "gn:population":0,
    "gn:timezone":"Pacific/Guadalcanal",
    "iso:country":"SB",
    "wof:name":"Selavana",
    "wof:placetype":"locality"
},
  "geometry": {"coordinates":[160.27879999999999,-9.499],"type":"Point"}
}