{
  "type": "Feature",
  "properties": {
    "gn:admin1_code":"0.0",
    "gn:asciiname":"Kolovatuniura",
    "gn:country_code":"SB",
    "gn:dem":130,
    "gn:feature_class":"P",
    "gn:feature_code":"PPL",
    "gn:name":"Kolovatuniura",
    "gn:population":0,
    "gn:timezone":"Pacific/Guadalcanal",
    "iso:country":"SB",
    "wof:name":"Kolovatuniura",
    "wof:placetype":"locality"
},
  "geometry": {"coordinates":[160.59277,-9.68243],"type":"Point"}
}