{
  "type": "Feature",
  "properties": {
    "gn:admin1_code":"0.0",
    "gn:asciiname":"Ote",
    "gn:country_code":"SB",
    "gn:dem":15,
    "gn:feature_class":"P",
    "gn:feature_code":"PPL",
    "gn:name":"Ote",
    "gn:population":0,
    "gn:timezone":"Pacific/Guadalcanal",
    "iso:country":"SB",
    "wof:name":"Ote",
    "wof:placetype":"locality"
},
  "geometry": {"coordinates":[161.54501000000005,-9.61718],"type":"Point"}
}