{
  "type": "Feature",
  "properties": {
    "gn:admin1_code":"0.0",
    "gn:asciiname":"Mbiula",
    "gn:country_code":"SB",
    "gn:dem":32,
    "gn:feature_class":"P",
    "gn:feature_code":"PPL",
    "gn:name":"Mbiula",
    "gn:population":0,
    "gn:timezone":"Pacific/Guadalcanal",
    "iso:country":"SB",
    "wof:name":"Mbiula",
    "wof:placetype":"locality"
},
  "geometry": {"coordinates":[157.42831000000001,-8.26405],"type":"Point"}
}