{
  "type": "Feature",
  "properties": {
    "gn:admin1_code":"0.0",
    "gn:asciiname":"Oula",
    "gn:country_code":"SB",
    "gn:dem":1,
    "gn:feature_class":"P",
    "gn:feature_code":"PPL",
    "gn:name":"Oula",
    "gn:population":0,
    "gn:timezone":"Pacific/Guadalcanal",
    "iso:country":"SB",
    "name:por_x_preferred":[
        "Ula"
    ],
    "name:vie_x_preferred":[
        "Oula"
    ],
    "wof:name":"Oula",
    "wof:placetype":"locality"
},
  "geometry": {"coordinates":[156.58333000000005,-7.78333],"type":"Point"}
}