{
  "type": "Feature",
  "properties": {
    "gn:admin1_code":"0.0",
    "gn:asciiname":"Ghulavu",
    "gn:country_code":"SB",
    "gn:dem":13,
    "gn:feature_class":"P",
    "gn:feature_code":"PPL",
    "gn:name":"Ghulavu",
    "gn:population":0,
    "gn:timezone":"Pacific/Guadalcanal",
    "iso:country":"SB",
    "name:und_x_variant":[
        "Nulavu",
        "Hulavu",
        "Lavu",
        "Ghulavu"
    ],
    "wof:name":"Ghulavu",
    "wof:placetype":"locality"
},
  "geometry": {"coordinates":[159.60178999999999,-9.39528],"type":"Point"}
}