{
  "type": "Feature",
  "properties": {
    "gn:admin1_code":"0.0",
    "gn:asciiname":"Haimarao",
    "gn:country_code":"SB",
    "gn:dem":12,
    "gn:feature_class":"P",
    "gn:feature_code":"PPL",
    "gn:name":"Haimarao",
    "gn:population":0,
    "gn:timezone":"Pacific/Guadalcanal",
    "iso:country":"SB",
    "wof:name":"Haimarao",
    "wof:placetype":"locality"
},
  "geometry": {"coordinates":[160.41128,-9.86806],"type":"Point"}
}