{
  "type": "Feature",
  "properties": {
    "gn:admin1_code":"0.0",
    "gn:asciiname":"Luti",
    "gn:country_code":"SB",
    "gn:dem":10,
    "gn:feature_class":"P",
    "gn:feature_code":"PPL",
    "gn:name":"Luti",
    "gn:population":0,
    "gn:timezone":"Pacific/Guadalcanal",
    "iso:country":"SB",
    "wof:name":"Luti",
    "wof:placetype":"locality"
},
  "geometry": {"coordinates":[156.98213000000001,-7.23564],"type":"Point"}
}