{
  "type": "Feature",
  "properties": {
    "gn:admin1_code":"0.0",
    "gn:asciiname":"Kolomosu",
    "gn:country_code":"SB",
    "gn:dem":27,
    "gn:feature_class":"P",
    "gn:feature_code":"PPL",
    "gn:name":"Kolomosu",
    "gn:population":0,
    "gn:timezone":"Pacific/Guadalcanal",
    "iso:country":"SB",
    "wof:name":"Kolomosu",
    "wof:placetype":"locality"
},
  "geometry": {"coordinates":[159.69533999999999,-8.22304],"type":"Point"}
}