{
  "type": "Feature",
  "properties": {
    "gn:admin1_code":"0.0",
    "gn:asciiname":"Poianiho",
    "gn:country_code":"SB",
    "gn:dem":8,
    "gn:feature_class":"P",
    "gn:feature_code":"PPL",
    "gn:name":"Poianiho",
    "gn:population":0,
    "gn:timezone":"Pacific/Guadalcanal",
    "iso:country":"SB",
    "name:und_x_variant":[
        "Poinahoho",
        "Poinagobo",
        "Poianiho"
    ],
    "wof:name":"Poianiho",
    "wof:placetype":"locality"
},
  "geometry": {"coordinates":[160.80760000000001,-9.87644],"type":"Point"}
}