{
  "type": "Feature",
  "properties": {
    "gn:asciiname":"Kocho",
    "gn:country_code":"SB",
    "gn:dem":17,
    "gn:feature_class":"P",
    "gn:feature_code":"PPL",
    "gn:name":"Kocho",
    "gn:population":0,
    "gn:timezone":"Pacific/Guadalcanal",
    "iso:country":"SB",
    "wof:name":"Kocho",
    "wof:placetype":"locality"
},
  "geometry": {"coordinates":[156.53599,-8.24547],"type":"Point"}
}