{
  "type": "Feature",
  "properties": {
    "gn:admin1_code":"0.0",
    "gn:asciiname":"Reko",
    "gn:country_code":"SB",
    "gn:dem":16,
    "gn:feature_class":"P",
    "gn:feature_code":"PPL",
    "gn:name":"Reko",
    "gn:population":0,
    "gn:timezone":"Pacific/Guadalcanal",
    "iso:country":"SB",
    "wof:name":"Reko",
    "wof:placetype":"locality"
},
  "geometry": {"coordinates":[159.80781999999999,-9.16153],"type":"Point"}
}