{
  "type": "Feature",
  "properties": {
    "gn:admin1_code":"0.0",
    "gn:asciiname":"Numbuko",
    "gn:country_code":"SB",
    "gn:dem":15,
    "gn:feature_class":"P",
    "gn:feature_code":"PPL",
    "gn:name":"Numbuko",
    "gn:population":0,
    "gn:timezone":"Pacific/Guadalcanal",
    "iso:country":"SB",
    "wof:name":"Numbuko",
    "wof:placetype":"locality"
},
  "geometry": {"coordinates":[166.92136000000005,-11.6547],"type":"Point"}
}