{
  "type": "Feature",
  "properties": {
    "gn:admin1_code":"0.0",
    "gn:asciiname":"Chokare",
    "gn:country_code":"SB",
    "gn:dem":57,
    "gn:feature_class":"P",
    "gn:feature_code":"PPL",
    "gn:name":"Chokare",
    "gn:population":0,
    "gn:timezone":"Pacific/Guadalcanal",
    "iso:country":"SB",
    "wof:name":"Chokare",
    "wof:placetype":"locality"
},
  "geometry": {"coordinates":[160.41387,-9.58772],"type":"Point"}
}