{
  "type": "Feature",
  "properties": {
    "gn:admin1_code":"0.0",
    "gn:asciiname":"Kuma'ihavi",
    "gn:country_code":"SB",
    "gn:dem":25,
    "gn:feature_class":"P",
    "gn:feature_code":"PPL",
    "gn:name":"Kuma\u2019ihavi",
    "gn:population":0,
    "gn:timezone":"Pacific/Guadalcanal",
    "iso:country":"SB",
    "wof:name":"Kuma'ihavi",
    "wof:placetype":"locality"
},
  "geometry": {"coordinates":[159.68866,-8.27091],"type":"Point"}
}