{
  "type": "Feature",
  "properties": {
    "gn:admin1_code":"0.0",
    "gn:asciiname":"Kokoilo",
    "gn:country_code":"SB",
    "gn:dem":72,
    "gn:feature_class":"P",
    "gn:feature_code":"PPL",
    "gn:name":"Kokoilo",
    "gn:population":0,
    "gn:timezone":"Pacific/Guadalcanal",
    "iso:country":"SB",
    "wof:name":"Kokoilo",
    "wof:placetype":"locality"
},
  "geometry": {"coordinates":[159.84878,-9.4299],"type":"Point"}
}