{
  "type": "Feature",
  "properties": {
    "gn:admin1_code":"0.0",
    "gn:asciiname":"Ghurumei",
    "gn:country_code":"SB",
    "gn:dem":8,
    "gn:feature_class":"P",
    "gn:feature_code":"PPL",
    "gn:name":"Ghurumei",
    "gn:population":0,
    "gn:timezone":"Pacific/Guadalcanal",
    "iso:country":"SB",
    "wof:name":"Ghurumei",
    "wof:placetype":"locality"
},
  "geometry": {"coordinates":[159.76740000000001,-8.27989],"type":"Point"}
}