{
  "type": "Feature",
  "properties": {
    "gn:admin1_code":"0.0",
    "gn:asciiname":"Fanuafalai",
    "gn:country_code":"SB",
    "gn:dem":735,
    "gn:feature_class":"P",
    "gn:feature_code":"PPL",
    "gn:name":"Fanuafalai",
    "gn:population":0,
    "gn:timezone":"Pacific/Guadalcanal",
    "iso:country":"SB",
    "wof:name":"Fanuafalai",
    "wof:placetype":"locality"
},
  "geometry": {"coordinates":[161.04273000000001,-8.93609],"type":"Point"}
}