{
  "type": "Feature",
  "properties": {
    "gn:admin1_code":"0.0",
    "gn:asciiname":"Kologhona",
    "gn:country_code":"SB",
    "gn:dem":36,
    "gn:feature_class":"P",
    "gn:feature_code":"PPL",
    "gn:name":"Kologhona",
    "gn:population":0,
    "gn:timezone":"Pacific/Guadalcanal",
    "iso:country":"SB",
    "wof:name":"Kologhona",
    "wof:placetype":"locality"
},
  "geometry": {"coordinates":[159.82138999999995,-9.73099],"type":"Point"}
}