{
  "type": "Feature",
  "properties": {
    "gn:admin1_code":"0.0",
    "gn:asciiname":"Nama",
    "gn:country_code":"SB",
    "gn:dem":1,
    "gn:feature_class":"P",
    "gn:feature_code":"PPL",
    "gn:name":"Nama",
    "gn:population":0,
    "gn:timezone":"Pacific/Guadalcanal",
    "iso:country":"SB",
    "wof:name":"Nama",
    "wof:placetype":"locality"
},
  "geometry": {"coordinates":[166.78333000000001,-11.61667],"type":"Point"}
}