{
  "type": "Feature",
  "properties": {
    "gn:admin1_code":"0.0",
    "gn:asciiname":"Ololo",
    "gn:country_code":"SB",
    "gn:dem":18,
    "gn:feature_class":"P",
    "gn:feature_code":"PPL",
    "gn:name":"Ololo",
    "gn:population":0,
    "gn:timezone":"Pacific/Guadalcanal",
    "iso:country":"SB",
    "wof:name":"Ololo",
    "wof:placetype":"locality"
},
  "geometry": {"coordinates":[160.64789999999999,-8.44615],"type":"Point"}
}