{
  "type": "Feature",
  "properties": {
    "gn:admin1_code":"0.0",
    "gn:asciiname":"Na Ande",
    "gn:country_code":"SB",
    "gn:dem":295,
    "gn:feature_class":"P",
    "gn:feature_code":"PPL",
    "gn:name":"Na Ande",
    "gn:population":0,
    "gn:timezone":"Pacific/Guadalcanal",
    "iso:country":"SB",
    "wof:name":"Na Ande",
    "wof:placetype":"locality"
},
  "geometry": {"coordinates":[160.63073,-9.79953],"type":"Point"}
}