{
  "type": "Feature",
  "properties": {
    "gn:admin1_code":"0.0",
    "gn:asciiname":"Maisu",
    "gn:country_code":"SB",
    "gn:dem":39,
    "gn:feature_class":"P",
    "gn:feature_code":"PPL",
    "gn:name":"Maisu",
    "gn:population":0,
    "gn:timezone":"Pacific/Guadalcanal",
    "iso:country":"SB",
    "wof:name":"Maisu",
    "wof:placetype":"locality"
},
  "geometry": {"coordinates":[159.73136,-9.72077],"type":"Point"}
}